src/dco_nco.v
module dco_nco #(
    parameter WIDTH = 32  // Accumulator width. Higher = finer frequency resolution
)(
    input  wire             sys_clk,      // System clock (e.g., 100MHz)
    input  wire             rst_n,        // Active low reset
    input  wire [WIDTH-1:0] tuning_word,  // Control input (sets frequency)
    output wire             dco_out       // Generated output clock
);

    // The Phase Accumulator
    reg [WIDTH-1:0] accumulator;

    always @(posedge sys_clk or negedge rst_n) begin
        if (!rst_n) begin
            accumulator <= {WIDTH{1'b0}};
        end else begin
            // Increment phase by the tuning word every cycle
            accumulator <= accumulator + tuning_word;
        end
    end

    // The MSB is the output clock (50% duty cycle on average, but with jitter)
    assign dco_out = accumulator[WIDTH-1];

endmodule

test/tb_dco.v
module tb_dco;

    reg clk;
    reg rst_n;
    reg [31:0] tuning_word;
    wire dco_out;

    // Instantiate the DCO
    dco_nco #(.WIDTH(32)) u_dco (
        .sys_clk(clk),
        .rst_n(rst_n),
        .tuning_word(tuning_word),
        .dco_out(dco_out)
    );

    // Generate 100 MHz System Clock
    always #5 clk = ~clk; 

    initial begin
        // --- VCD DUMPING COMMANDS START HERE ---
        $dumpfile("test/dco_tb.vcd");   // 1. Set the output filename
        $dumpvars(0, tb_dco);           // 2. Dump all signals in 'tb_dco' hierarchy
        // ---------------------------------------
        // Init
        clk = 0;
        rst_n = 0;
        tuning_word = 0;
        
        // Release Reset
        #100 rst_n = 1;

        // Test Case 1: Low Frequency
        // Formula: Target 1 MHz output with 100 MHz sys_clk
        // Tuning = (1M / 100M) * 2^32 approx 42949673
        tuning_word = 32'd42949673;
        $display("Setting DCO to approx 1 MHz");
        #20000; // Run for a bit

        // Test Case 2: High Frequency (Double it)
        tuning_word = 32'd85899346; 
        $display("Setting DCO to approx 2 MHz");
        #20000;

        $finish;
    end
endmodule

test/dco_tb.vcd
$date
	Sat Dec 13 14:39:47 2025
$end
$version
	Icarus Verilog
$end
$timescale
	1s
$end
$scope module tb_dco $end
$var wire 1 ! dco_out $end
$var reg 1 " clk $end
$var reg 1 # rst_n $end
$var reg 32 $ tuning_word [31:0] $end
$scope module u_dco $end
$var wire 1 # rst_n $end
$var wire 1 " sys_clk $end
$var wire 32 % tuning_word [31:0] $end
$var wire 1 ! dco_out $end
$var parameter 32 & WIDTH $end
$var reg 32 ' accumulator [31:0] $end
$upscope $end
$upscope $end
$enddefinitions $end
$comment Show the parameter values. $end
$dumpall
b100000 &
$end
#0
$dumpvars
b0 '
b0 %
b0 $
0#
0"
0!
$end
#5
1"
#10
0"
#15
1"
#20
0"
#25
1"
#30
0"
#35
1"
#40
0"
#45
1"
#50
0"
#55
1"
#60
0"
#65
1"
#70
0"
#75
1"
#80
0"
#85
1"
#90
0"
#95
1"
#100
0"
b10100011110101110000101001 $
b10100011110101110000101001 %
1#
#105
b10100011110101110000101001 '
1"
#110
0"
#115
b101000111101011100001010010 '
1"
#120
0"
#125
b111101011100001010001111011 '
1"
#130
0"
#135
b1010001111010111000010100100 '
1"
#140
0"
#145
b1100110011001100110011001101 '
1"
#150
0"
#155
b1111010111000010100011110110 '
1"
#160
0"
#165
b10001111010111000010100011111 '
1"
#170
0"
#175
b10100011110101110000101001000 '
1"
#180
0"
#185
b10111000010100011110101110001 '
1"
#190
0"
#195
b11001100110011001100110011010 '
1"
#200
0"
#205
b11100001010001111010111000011 '
1"
#210
0"
#215
b11110101110000101000111101100 '
1"
#220
0"
#225
b100001010001111010111000010101 '
1"
#230
0"
#235
b100011110101110000101000111110 '
1"
#240
0"
#245
b100110011001100110011001100111 '
1"
#250
0"
#255
b101000111101011100001010010000 '
1"
#260
0"
#265
b101011100001010001111010111001 '
1"
#270
0"
#275
b101110000101000111101011100010 '
1"
#280
0"
#285
b110000101000111101011100001011 '
1"
#290
0"
#295
b110011001100110011001100110100 '
1"
#300
0"
#305
b110101110000101000111101011101 '
1"
#310
0"
#315
b111000010100011110101110000110 '
1"
#320
0"
#325
b111010111000010100011110101111 '
1"
#330
0"
#335
b111101011100001010001111011000 '
1"
#340
0"
#345
b1000000000000000000000000000001 '
1"
#350
0"
#355
b1000010100011110101110000101010 '
1"
#360
0"
#365
b1000101000111101011100001010011 '
1"
#370
0"
#375
b1000111101011100001010001111100 '
1"
#380
0"
#385
b1001010001111010111000010100101 '
1"
#390
0"
#395
b1001100110011001100110011001110 '
1"
#400
0"
#405
b1001111010111000010100011110111 '
1"
#410
0"
#415
b1010001111010111000010100100000 '
1"
#420
0"
#425
b1010100011110101110000101001001 '
1"
#430
0"
#435
b1010111000010100011110101110010 '
1"
#440
0"
#445
b1011001100110011001100110011011 '
1"
#450
0"
#455
b1011100001010001111010111000100 '
1"
#460
0"
#465
b1011110101110000101000111101101 '
1"
#470
0"
#475
b1100001010001111010111000010110 '
1"
#480
0"
#485
b1100011110101110000101000111111 '
1"
#490
0"
#495
b1100110011001100110011001101000 '
1"
#500
0"
#505
b1101000111101011100001010010001 '
1"
#510
0"
#515
b1101011100001010001111010111010 '
1"
#520
0"
#525
b1101110000101000111101011100011 '
1"
#530
0"
#535
b1110000101000111101011100001100 '
1"
#540
0"
#545
b1110011001100110011001100110101 '
1"
#550
0"
#555
b1110101110000101000111101011110 '
1"
#560
0"
#565
b1111000010100011110101110000111 '
1"
#570
0"
#575
b1111010111000010100011110110000 '
1"
#580
0"
#585
b1111101011100001010001111011001 '
1"
#590
0"
#595
1!
b10000000000000000000000000000010 '
1"
#600
0"
#605
b10000010100011110101110000101011 '
1"
#610
0"
#615
b10000101000111101011100001010100 '
1"
#620
0"
#625
b10000111101011100001010001111101 '
1"
#630
0"
#635
b10001010001111010111000010100110 '
1"
#640
0"
#645
b10001100110011001100110011001111 '
1"
#650
0"
#655
b10001111010111000010100011111000 '
1"
#660
0"
#665
b10010001111010111000010100100001 '
1"
#670
0"
#675
b10010100011110101110000101001010 '
1"
#680
0"
#685
b10010111000010100011110101110011 '
1"
#690
0"
#695
b10011001100110011001100110011100 '
1"
#700
0"
#705
b10011100001010001111010111000101 '
1"
#710
0"
#715
b10011110101110000101000111101110 '
1"
#720
0"
#725
b10100001010001111010111000010111 '
1"
#730
0"
#735
b10100011110101110000101001000000 '
1"
#740
0"
#745
b10100110011001100110011001101001 '
1"
#750
0"
#755
b10101000111101011100001010010010 '
1"
#760
0"
#765
b10101011100001010001111010111011 '
1"
#770
0"
#775
b10101110000101000111101011100100 '
1"
#780
0"
#785
b10110000101000111101011100001101 '
1"
#790
0"
#795
b10110011001100110011001100110110 '
1"
#800
0"
#805
b10110101110000101000111101011111 '
1"
#810
0"
#815
b10111000010100011110101110001000 '
1"
#820
0"
#825
b10111010111000010100011110110001 '
1"
#830
0"
#835
b10111101011100001010001111011010 '
1"
#840
0"
#845
b11000000000000000000000000000011 '
1"
#850
0"
#855
b11000010100011110101110000101100 '
1"
#860
0"
#865
b11000101000111101011100001010101 '
1"
#870
0"
#875
b11000111101011100001010001111110 '
1"
#880
0"
#885
b11001010001111010111000010100111 '
1"
#890
0"
#895
b11001100110011001100110011010000 '
1"
#900
0"
#905
b11001111010111000010100011111001 '
1"
#910
0"
#915
b11010001111010111000010100100010 '
1"
#920
0"
#925
b11010100011110101110000101001011 '
1"
#930
0"
#935
b11010111000010100011110101110100 '
1"
#940
0"
#945
b11011001100110011001100110011101 '
1"
#950
0"
#955
b11011100001010001111010111000110 '
1"
#960
0"
#965
b11011110101110000101000111101111 '
1"
#970
0"
#975
b11100001010001111010111000011000 '
1"
#980
0"
#985
b11100011110101110000101001000001 '
1"
#990
0"
#995
b11100110011001100110011001101010 '
1"
#1000
0"
#1005
b11101000111101011100001010010011 '
1"
#1010
0"
#1015
b11101011100001010001111010111100 '
1"
#1020
0"
#1025
b11101110000101000111101011100101 '
1"
#1030
0"
#1035
b11110000101000111101011100001110 '
1"
#1040
0"
#1045
b11110011001100110011001100110111 '
1"
#1050
0"
#1055
b11110101110000101000111101100000 '
1"
#1060
0"
#1065
b11111000010100011110101110001001 '
1"
#1070
0"
#1075
b11111010111000010100011110110010 '
1"
#1080
0"
#1085
b11111101011100001010001111011011 '
1"
#1090
0"
#1095
0!
b100 '
1"
#1100
0"
#1105
b10100011110101110000101101 '
1"
#1110
0"
#1115
b101000111101011100001010110 '
1"
#1120
0"
#1125
b111101011100001010001111111 '
1"
#1130
0"
#1135
b1010001111010111000010101000 '
1"
#1140
0"
#1145
b1100110011001100110011010001 '
1"
#1150
0"
#1155
b1111010111000010100011111010 '
1"
#1160
0"
#1165
b10001111010111000010100100011 '
1"
#1170
0"
#1175
b10100011110101110000101001100 '
1"
#1180
0"
#1185
b10111000010100011110101110101 '
1"
#1190
0"
#1195
b11001100110011001100110011110 '
1"
#1200
0"
#1205
b11100001010001111010111000111 '
1"
#1210
0"
#1215
b11110101110000101000111110000 '
1"
#1220
0"
#1225
b100001010001111010111000011001 '
1"
#1230
0"
#1235
b100011110101110000101001000010 '
1"
#1240
0"
#1245
b100110011001100110011001101011 '
1"
#1250
0"
#1255
b101000111101011100001010010100 '
1"
#1260
0"
#1265
b101011100001010001111010111101 '
1"
#1270
0"
#1275
b101110000101000111101011100110 '
1"
#1280
0"
#1285
b110000101000111101011100001111 '
1"
#1290
0"
#1295
b110011001100110011001100111000 '
1"
#1300
0"
#1305
b110101110000101000111101100001 '
1"
#1310
0"
#1315
b111000010100011110101110001010 '
1"
#1320
0"
#1325
b111010111000010100011110110011 '
1"
#1330
0"
#1335
b111101011100001010001111011100 '
1"
#1340
0"
#1345
b1000000000000000000000000000101 '
1"
#1350
0"
#1355
b1000010100011110101110000101110 '
1"
#1360
0"
#1365
b1000101000111101011100001010111 '
1"
#1370
0"
#1375
b1000111101011100001010010000000 '
1"
#1380
0"
#1385
b1001010001111010111000010101001 '
1"
#1390
0"
#1395
b1001100110011001100110011010010 '
1"
#1400
0"
#1405
b1001111010111000010100011111011 '
1"
#1410
0"
#1415
b1010001111010111000010100100100 '
1"
#1420
0"
#1425
b1010100011110101110000101001101 '
1"
#1430
0"
#1435
b1010111000010100011110101110110 '
1"
#1440
0"
#1445
b1011001100110011001100110011111 '
1"
#1450
0"
#1455
b1011100001010001111010111001000 '
1"
#1460
0"
#1465
b1011110101110000101000111110001 '
1"
#1470
0"
#1475
b1100001010001111010111000011010 '
1"
#1480
0"
#1485
b1100011110101110000101001000011 '
1"
#1490
0"
#1495
b1100110011001100110011001101100 '
1"
#1500
0"
#1505
b1101000111101011100001010010101 '
1"
#1510
0"
#1515
b1101011100001010001111010111110 '
1"
#1520
0"
#1525
b1101110000101000111101011100111 '
1"
#1530
0"
#1535
b1110000101000111101011100010000 '
1"
#1540
0"
#1545
b1110011001100110011001100111001 '
1"
#1550
0"
#1555
b1110101110000101000111101100010 '
1"
#1560
0"
#1565
b1111000010100011110101110001011 '
1"
#1570
0"
#1575
b1111010111000010100011110110100 '
1"
#1580
0"
#1585
b1111101011100001010001111011101 '
1"
#1590
0"
#1595
1!
b10000000000000000000000000000110 '
1"
#1600
0"
#1605
b10000010100011110101110000101111 '
1"
#1610
0"
#1615
b10000101000111101011100001011000 '
1"
#1620
0"
#1625
b10000111101011100001010010000001 '
1"
#1630
0"
#1635
b10001010001111010111000010101010 '
1"
#1640
0"
#1645
b10001100110011001100110011010011 '
1"
#1650
0"
#1655
b10001111010111000010100011111100 '
1"
#1660
0"
#1665
b10010001111010111000010100100101 '
1"
#1670
0"
#1675
b10010100011110101110000101001110 '
1"
#1680
0"
#1685
b10010111000010100011110101110111 '
1"
#1690
0"
#1695
b10011001100110011001100110100000 '
1"
#1700
0"
#1705
b10011100001010001111010111001001 '
1"
#1710
0"
#1715
b10011110101110000101000111110010 '
1"
#1720
0"
#1725
b10100001010001111010111000011011 '
1"
#1730
0"
#1735
b10100011110101110000101001000100 '
1"
#1740
0"
#1745
b10100110011001100110011001101101 '
1"
#1750
0"
#1755
b10101000111101011100001010010110 '
1"
#1760
0"
#1765
b10101011100001010001111010111111 '
1"
#1770
0"
#1775
b10101110000101000111101011101000 '
1"
#1780
0"
#1785
b10110000101000111101011100010001 '
1"
#1790
0"
#1795
b10110011001100110011001100111010 '
1"
#1800
0"
#1805
b10110101110000101000111101100011 '
1"
#1810
0"
#1815
b10111000010100011110101110001100 '
1"
#1820
0"
#1825
b10111010111000010100011110110101 '
1"
#1830
0"
#1835
b10111101011100001010001111011110 '
1"
#1840
0"
#1845
b11000000000000000000000000000111 '
1"
#1850
0"
#1855
b11000010100011110101110000110000 '
1"
#1860
0"
#1865
b11000101000111101011100001011001 '
1"
#1870
0"
#1875
b11000111101011100001010010000010 '
1"
#1880
0"
#1885
b11001010001111010111000010101011 '
1"
#1890
0"
#1895
b11001100110011001100110011010100 '
1"
#1900
0"
#1905
b11001111010111000010100011111101 '
1"
#1910
0"
#1915
b11010001111010111000010100100110 '
1"
#1920
0"
#1925
b11010100011110101110000101001111 '
1"
#1930
0"
#1935
b11010111000010100011110101111000 '
1"
#1940
0"
#1945
b11011001100110011001100110100001 '
1"
#1950
0"
#1955
b11011100001010001111010111001010 '
1"
#1960
0"
#1965
b11011110101110000101000111110011 '
1"
#1970
0"
#1975
b11100001010001111010111000011100 '
1"
#1980
0"
#1985
b11100011110101110000101001000101 '
1"
#1990
0"
#1995
b11100110011001100110011001101110 '
1"
#2000
0"
#2005
b11101000111101011100001010010111 '
1"
#2010
0"
#2015
b11101011100001010001111011000000 '
1"
#2020
0"
#2025
b11101110000101000111101011101001 '
1"
#2030
0"
#2035
b11110000101000111101011100010010 '
1"
#2040
0"
#2045
b11110011001100110011001100111011 '
1"
#2050
0"
#2055
b11110101110000101000111101100100 '
1"
#2060
0"
#2065
b11111000010100011110101110001101 '
1"
#2070
0"
#2075
b11111010111000010100011110110110 '
1"
#2080
0"
#2085
b11111101011100001010001111011111 '
1"
#2090
0"
#2095
0!
b1000 '
1"
#2100
0"
#2105
b10100011110101110000110001 '
1"
#2110
0"
#2115
b101000111101011100001011010 '
1"
#2120
0"
#2125
b111101011100001010010000011 '
1"
#2130
0"
#2135
b1010001111010111000010101100 '
1"
#2140
0"
#2145
b1100110011001100110011010101 '
1"
#2150
0"
#2155
b1111010111000010100011111110 '
1"
#2160
0"
#2165
b10001111010111000010100100111 '
1"
#2170
0"
#2175
b10100011110101110000101010000 '
1"
#2180
0"
#2185
b10111000010100011110101111001 '
1"
#2190
0"
#2195
b11001100110011001100110100010 '
1"
#2200
0"
#2205
b11100001010001111010111001011 '
1"
#2210
0"
#2215
b11110101110000101000111110100 '
1"
#2220
0"
#2225
b100001010001111010111000011101 '
1"
#2230
0"
#2235
b100011110101110000101001000110 '
1"
#2240
0"
#2245
b100110011001100110011001101111 '
1"
#2250
0"
#2255
b101000111101011100001010011000 '
1"
#2260
0"
#2265
b101011100001010001111011000001 '
1"
#2270
0"
#2275
b101110000101000111101011101010 '
1"
#2280
0"
#2285
b110000101000111101011100010011 '
1"
#2290
0"
#2295
b110011001100110011001100111100 '
1"
#2300
0"
#2305
b110101110000101000111101100101 '
1"
#2310
0"
#2315
b111000010100011110101110001110 '
1"
#2320
0"
#2325
b111010111000010100011110110111 '
1"
#2330
0"
#2335
b111101011100001010001111100000 '
1"
#2340
0"
#2345
b1000000000000000000000000001001 '
1"
#2350
0"
#2355
b1000010100011110101110000110010 '
1"
#2360
0"
#2365
b1000101000111101011100001011011 '
1"
#2370
0"
#2375
b1000111101011100001010010000100 '
1"
#2380
0"
#2385
b1001010001111010111000010101101 '
1"
#2390
0"
#2395
b1001100110011001100110011010110 '
1"
#2400
0"
#2405
b1001111010111000010100011111111 '
1"
#2410
0"
#2415
b1010001111010111000010100101000 '
1"
#2420
0"
#2425
b1010100011110101110000101010001 '
1"
#2430
0"
#2435
b1010111000010100011110101111010 '
1"
#2440
0"
#2445
b1011001100110011001100110100011 '
1"
#2450
0"
#2455
b1011100001010001111010111001100 '
1"
#2460
0"
#2465
b1011110101110000101000111110101 '
1"
#2470
0"
#2475
b1100001010001111010111000011110 '
1"
#2480
0"
#2485
b1100011110101110000101001000111 '
1"
#2490
0"
#2495
b1100110011001100110011001110000 '
1"
#2500
0"
#2505
b1101000111101011100001010011001 '
1"
#2510
0"
#2515
b1101011100001010001111011000010 '
1"
#2520
0"
#2525
b1101110000101000111101011101011 '
1"
#2530
0"
#2535
b1110000101000111101011100010100 '
1"
#2540
0"
#2545
b1110011001100110011001100111101 '
1"
#2550
0"
#2555
b1110101110000101000111101100110 '
1"
#2560
0"
#2565
b1111000010100011110101110001111 '
1"
#2570
0"
#2575
b1111010111000010100011110111000 '
1"
#2580
0"
#2585
b1111101011100001010001111100001 '
1"
#2590
0"
#2595
1!
b10000000000000000000000000001010 '
1"
#2600
0"
#2605
b10000010100011110101110000110011 '
1"
#2610
0"
#2615
b10000101000111101011100001011100 '
1"
#2620
0"
#2625
b10000111101011100001010010000101 '
1"
#2630
0"
#2635
b10001010001111010111000010101110 '
1"
#2640
0"
#2645
b10001100110011001100110011010111 '
1"
#2650
0"
#2655
b10001111010111000010100100000000 '
1"
#2660
0"
#2665
b10010001111010111000010100101001 '
1"
#2670
0"
#2675
b10010100011110101110000101010010 '
1"
#2680
0"
#2685
b10010111000010100011110101111011 '
1"
#2690
0"
#2695
b10011001100110011001100110100100 '
1"
#2700
0"
#2705
b10011100001010001111010111001101 '
1"
#2710
0"
#2715
b10011110101110000101000111110110 '
1"
#2720
0"
#2725
b10100001010001111010111000011111 '
1"
#2730
0"
#2735
b10100011110101110000101001001000 '
1"
#2740
0"
#2745
b10100110011001100110011001110001 '
1"
#2750
0"
#2755
b10101000111101011100001010011010 '
1"
#2760
0"
#2765
b10101011100001010001111011000011 '
1"
#2770
0"
#2775
b10101110000101000111101011101100 '
1"
#2780
0"
#2785
b10110000101000111101011100010101 '
1"
#2790
0"
#2795
b10110011001100110011001100111110 '
1"
#2800
0"
#2805
b10110101110000101000111101100111 '
1"
#2810
0"
#2815
b10111000010100011110101110010000 '
1"
#2820
0"
#2825
b10111010111000010100011110111001 '
1"
#2830
0"
#2835
b10111101011100001010001111100010 '
1"
#2840
0"
#2845
b11000000000000000000000000001011 '
1"
#2850
0"
#2855
b11000010100011110101110000110100 '
1"
#2860
0"
#2865
b11000101000111101011100001011101 '
1"
#2870
0"
#2875
b11000111101011100001010010000110 '
1"
#2880
0"
#2885
b11001010001111010111000010101111 '
1"
#2890
0"
#2895
b11001100110011001100110011011000 '
1"
#2900
0"
#2905
b11001111010111000010100100000001 '
1"
#2910
0"
#2915
b11010001111010111000010100101010 '
1"
#2920
0"
#2925
b11010100011110101110000101010011 '
1"
#2930
0"
#2935
b11010111000010100011110101111100 '
1"
#2940
0"
#2945
b11011001100110011001100110100101 '
1"
#2950
0"
#2955
b11011100001010001111010111001110 '
1"
#2960
0"
#2965
b11011110101110000101000111110111 '
1"
#2970
0"
#2975
b11100001010001111010111000100000 '
1"
#2980
0"
#2985
b11100011110101110000101001001001 '
1"
#2990
0"
#2995
b11100110011001100110011001110010 '
1"
#3000
0"
#3005
b11101000111101011100001010011011 '
1"
#3010
0"
#3015
b11101011100001010001111011000100 '
1"
#3020
0"
#3025
b11101110000101000111101011101101 '
1"
#3030
0"
#3035
b11110000101000111101011100010110 '
1"
#3040
0"
#3045
b11110011001100110011001100111111 '
1"
#3050
0"
#3055
b11110101110000101000111101101000 '
1"
#3060
0"
#3065
b11111000010100011110101110010001 '
1"
#3070
0"
#3075
b11111010111000010100011110111010 '
1"
#3080
0"
#3085
b11111101011100001010001111100011 '
1"
#3090
0"
#3095
0!
b1100 '
1"
#3100
0"
#3105
b10100011110101110000110101 '
1"
#3110
0"
#3115
b101000111101011100001011110 '
1"
#3120
0"
#3125
b111101011100001010010000111 '
1"
#3130
0"
#3135
b1010001111010111000010110000 '
1"
#3140
0"
#3145
b1100110011001100110011011001 '
1"
#3150
0"
#3155
b1111010111000010100100000010 '
1"
#3160
0"
#3165
b10001111010111000010100101011 '
1"
#3170
0"
#3175
b10100011110101110000101010100 '
1"
#3180
0"
#3185
b10111000010100011110101111101 '
1"
#3190
0"
#3195
b11001100110011001100110100110 '
1"
#3200
0"
#3205
b11100001010001111010111001111 '
1"
#3210
0"
#3215
b11110101110000101000111111000 '
1"
#3220
0"
#3225
b100001010001111010111000100001 '
1"
#3230
0"
#3235
b100011110101110000101001001010 '
1"
#3240
0"
#3245
b100110011001100110011001110011 '
1"
#3250
0"
#3255
b101000111101011100001010011100 '
1"
#3260
0"
#3265
b101011100001010001111011000101 '
1"
#3270
0"
#3275
b101110000101000111101011101110 '
1"
#3280
0"
#3285
b110000101000111101011100010111 '
1"
#3290
0"
#3295
b110011001100110011001101000000 '
1"
#3300
0"
#3305
b110101110000101000111101101001 '
1"
#3310
0"
#3315
b111000010100011110101110010010 '
1"
#3320
0"
#3325
b111010111000010100011110111011 '
1"
#3330
0"
#3335
b111101011100001010001111100100 '
1"
#3340
0"
#3345
b1000000000000000000000000001101 '
1"
#3350
0"
#3355
b1000010100011110101110000110110 '
1"
#3360
0"
#3365
b1000101000111101011100001011111 '
1"
#3370
0"
#3375
b1000111101011100001010010001000 '
1"
#3380
0"
#3385
b1001010001111010111000010110001 '
1"
#3390
0"
#3395
b1001100110011001100110011011010 '
1"
#3400
0"
#3405
b1001111010111000010100100000011 '
1"
#3410
0"
#3415
b1010001111010111000010100101100 '
1"
#3420
0"
#3425
b1010100011110101110000101010101 '
1"
#3430
0"
#3435
b1010111000010100011110101111110 '
1"
#3440
0"
#3445
b1011001100110011001100110100111 '
1"
#3450
0"
#3455
b1011100001010001111010111010000 '
1"
#3460
0"
#3465
b1011110101110000101000111111001 '
1"
#3470
0"
#3475
b1100001010001111010111000100010 '
1"
#3480
0"
#3485
b1100011110101110000101001001011 '
1"
#3490
0"
#3495
b1100110011001100110011001110100 '
1"
#3500
0"
#3505
b1101000111101011100001010011101 '
1"
#3510
0"
#3515
b1101011100001010001111011000110 '
1"
#3520
0"
#3525
b1101110000101000111101011101111 '
1"
#3530
0"
#3535
b1110000101000111101011100011000 '
1"
#3540
0"
#3545
b1110011001100110011001101000001 '
1"
#3550
0"
#3555
b1110101110000101000111101101010 '
1"
#3560
0"
#3565
b1111000010100011110101110010011 '
1"
#3570
0"
#3575
b1111010111000010100011110111100 '
1"
#3580
0"
#3585
b1111101011100001010001111100101 '
1"
#3590
0"
#3595
1!
b10000000000000000000000000001110 '
1"
#3600
0"
#3605
b10000010100011110101110000110111 '
1"
#3610
0"
#3615
b10000101000111101011100001100000 '
1"
#3620
0"
#3625
b10000111101011100001010010001001 '
1"
#3630
0"
#3635
b10001010001111010111000010110010 '
1"
#3640
0"
#3645
b10001100110011001100110011011011 '
1"
#3650
0"
#3655
b10001111010111000010100100000100 '
1"
#3660
0"
#3665
b10010001111010111000010100101101 '
1"
#3670
0"
#3675
b10010100011110101110000101010110 '
1"
#3680
0"
#3685
b10010111000010100011110101111111 '
1"
#3690
0"
#3695
b10011001100110011001100110101000 '
1"
#3700
0"
#3705
b10011100001010001111010111010001 '
1"
#3710
0"
#3715
b10011110101110000101000111111010 '
1"
#3720
0"
#3725
b10100001010001111010111000100011 '
1"
#3730
0"
#3735
b10100011110101110000101001001100 '
1"
#3740
0"
#3745
b10100110011001100110011001110101 '
1"
#3750
0"
#3755
b10101000111101011100001010011110 '
1"
#3760
0"
#3765
b10101011100001010001111011000111 '
1"
#3770
0"
#3775
b10101110000101000111101011110000 '
1"
#3780
0"
#3785
b10110000101000111101011100011001 '
1"
#3790
0"
#3795
b10110011001100110011001101000010 '
1"
#3800
0"
#3805
b10110101110000101000111101101011 '
1"
#3810
0"
#3815
b10111000010100011110101110010100 '
1"
#3820
0"
#3825
b10111010111000010100011110111101 '
1"
#3830
0"
#3835
b10111101011100001010001111100110 '
1"
#3840
0"
#3845
b11000000000000000000000000001111 '
1"
#3850
0"
#3855
b11000010100011110101110000111000 '
1"
#3860
0"
#3865
b11000101000111101011100001100001 '
1"
#3870
0"
#3875
b11000111101011100001010010001010 '
1"
#3880
0"
#3885
b11001010001111010111000010110011 '
1"
#3890
0"
#3895
b11001100110011001100110011011100 '
1"
#3900
0"
#3905
b11001111010111000010100100000101 '
1"
#3910
0"
#3915
b11010001111010111000010100101110 '
1"
#3920
0"
#3925
b11010100011110101110000101010111 '
1"
#3930
0"
#3935
b11010111000010100011110110000000 '
1"
#3940
0"
#3945
b11011001100110011001100110101001 '
1"
#3950
0"
#3955
b11011100001010001111010111010010 '
1"
#3960
0"
#3965
b11011110101110000101000111111011 '
1"
#3970
0"
#3975
b11100001010001111010111000100100 '
1"
#3980
0"
#3985
b11100011110101110000101001001101 '
1"
#3990
0"
#3995
b11100110011001100110011001110110 '
1"
#4000
0"
#4005
b11101000111101011100001010011111 '
1"
#4010
0"
#4015
b11101011100001010001111011001000 '
1"
#4020
0"
#4025
b11101110000101000111101011110001 '
1"
#4030
0"
#4035
b11110000101000111101011100011010 '
1"
#4040
0"
#4045
b11110011001100110011001101000011 '
1"
#4050
0"
#4055
b11110101110000101000111101101100 '
1"
#4060
0"
#4065
b11111000010100011110101110010101 '
1"
#4070
0"
#4075
b11111010111000010100011110111110 '
1"
#4080
0"
#4085
b11111101011100001010001111100111 '
1"
#4090
0"
#4095
0!
b10000 '
1"
#4100
0"
#4105
b10100011110101110000111001 '
1"
#4110
0"
#4115
b101000111101011100001100010 '
1"
#4120
0"
#4125
b111101011100001010010001011 '
1"
#4130
0"
#4135
b1010001111010111000010110100 '
1"
#4140
0"
#4145
b1100110011001100110011011101 '
1"
#4150
0"
#4155
b1111010111000010100100000110 '
1"
#4160
0"
#4165
b10001111010111000010100101111 '
1"
#4170
0"
#4175
b10100011110101110000101011000 '
1"
#4180
0"
#4185
b10111000010100011110110000001 '
1"
#4190
0"
#4195
b11001100110011001100110101010 '
1"
#4200
0"
#4205
b11100001010001111010111010011 '
1"
#4210
0"
#4215
b11110101110000101000111111100 '
1"
#4220
0"
#4225
b100001010001111010111000100101 '
1"
#4230
0"
#4235
b100011110101110000101001001110 '
1"
#4240
0"
#4245
b100110011001100110011001110111 '
1"
#4250
0"
#4255
b101000111101011100001010100000 '
1"
#4260
0"
#4265
b101011100001010001111011001001 '
1"
#4270
0"
#4275
b101110000101000111101011110010 '
1"
#4280
0"
#4285
b110000101000111101011100011011 '
1"
#4290
0"
#4295
b110011001100110011001101000100 '
1"
#4300
0"
#4305
b110101110000101000111101101101 '
1"
#4310
0"
#4315
b111000010100011110101110010110 '
1"
#4320
0"
#4325
b111010111000010100011110111111 '
1"
#4330
0"
#4335
b111101011100001010001111101000 '
1"
#4340
0"
#4345
b1000000000000000000000000010001 '
1"
#4350
0"
#4355
b1000010100011110101110000111010 '
1"
#4360
0"
#4365
b1000101000111101011100001100011 '
1"
#4370
0"
#4375
b1000111101011100001010010001100 '
1"
#4380
0"
#4385
b1001010001111010111000010110101 '
1"
#4390
0"
#4395
b1001100110011001100110011011110 '
1"
#4400
0"
#4405
b1001111010111000010100100000111 '
1"
#4410
0"
#4415
b1010001111010111000010100110000 '
1"
#4420
0"
#4425
b1010100011110101110000101011001 '
1"
#4430
0"
#4435
b1010111000010100011110110000010 '
1"
#4440
0"
#4445
b1011001100110011001100110101011 '
1"
#4450
0"
#4455
b1011100001010001111010111010100 '
1"
#4460
0"
#4465
b1011110101110000101000111111101 '
1"
#4470
0"
#4475
b1100001010001111010111000100110 '
1"
#4480
0"
#4485
b1100011110101110000101001001111 '
1"
#4490
0"
#4495
b1100110011001100110011001111000 '
1"
#4500
0"
#4505
b1101000111101011100001010100001 '
1"
#4510
0"
#4515
b1101011100001010001111011001010 '
1"
#4520
0"
#4525
b1101110000101000111101011110011 '
1"
#4530
0"
#4535
b1110000101000111101011100011100 '
1"
#4540
0"
#4545
b1110011001100110011001101000101 '
1"
#4550
0"
#4555
b1110101110000101000111101101110 '
1"
#4560
0"
#4565
b1111000010100011110101110010111 '
1"
#4570
0"
#4575
b1111010111000010100011111000000 '
1"
#4580
0"
#4585
b1111101011100001010001111101001 '
1"
#4590
0"
#4595
1!
b10000000000000000000000000010010 '
1"
#4600
0"
#4605
b10000010100011110101110000111011 '
1"
#4610
0"
#4615
b10000101000111101011100001100100 '
1"
#4620
0"
#4625
b10000111101011100001010010001101 '
1"
#4630
0"
#4635
b10001010001111010111000010110110 '
1"
#4640
0"
#4645
b10001100110011001100110011011111 '
1"
#4650
0"
#4655
b10001111010111000010100100001000 '
1"
#4660
0"
#4665
b10010001111010111000010100110001 '
1"
#4670
0"
#4675
b10010100011110101110000101011010 '
1"
#4680
0"
#4685
b10010111000010100011110110000011 '
1"
#4690
0"
#4695
b10011001100110011001100110101100 '
1"
#4700
0"
#4705
b10011100001010001111010111010101 '
1"
#4710
0"
#4715
b10011110101110000101000111111110 '
1"
#4720
0"
#4725
b10100001010001111010111000100111 '
1"
#4730
0"
#4735
b10100011110101110000101001010000 '
1"
#4740
0"
#4745
b10100110011001100110011001111001 '
1"
#4750
0"
#4755
b10101000111101011100001010100010 '
1"
#4760
0"
#4765
b10101011100001010001111011001011 '
1"
#4770
0"
#4775
b10101110000101000111101011110100 '
1"
#4780
0"
#4785
b10110000101000111101011100011101 '
1"
#4790
0"
#4795
b10110011001100110011001101000110 '
1"
#4800
0"
#4805
b10110101110000101000111101101111 '
1"
#4810
0"
#4815
b10111000010100011110101110011000 '
1"
#4820
0"
#4825
b10111010111000010100011111000001 '
1"
#4830
0"
#4835
b10111101011100001010001111101010 '
1"
#4840
0"
#4845
b11000000000000000000000000010011 '
1"
#4850
0"
#4855
b11000010100011110101110000111100 '
1"
#4860
0"
#4865
b11000101000111101011100001100101 '
1"
#4870
0"
#4875
b11000111101011100001010010001110 '
1"
#4880
0"
#4885
b11001010001111010111000010110111 '
1"
#4890
0"
#4895
b11001100110011001100110011100000 '
1"
