src/divider.v
module divider (
    input  wire        clk_in,
    input  wire        rst_n,
    input  wire [31:0] div_val,
    output reg         clk_out
);

    reg [31:0] counter;

    always @(posedge clk_in or negedge rst_n) begin
        if (!rst_n) begin
            counter <= 0;
            clk_out <= 0;
        end else begin
            // 1. End of Cycle Check (Reset)
            if (counter >= div_val - 1) begin
                counter <= 0;
                clk_out <= 1'b1; // The next cycle (Cycle 0) is always High
            end else begin
                // 2. Normal Increment
                counter <= counter + 1;
                
                // 3. Duty Cycle Logic (FIXED)
                // We check if (counter + 1) is within the High phase.
                if ((counter + 1) < (div_val >> 1)) 
                    clk_out <= 1'b1;
                else
                    clk_out <= 1'b0;
            end
        end
    end
endmodule

src/dco_nco.v
module dco_nco #(
    parameter WIDTH = 32  // Accumulator width. Higher = finer frequency resolution
)(
    input  wire             sys_clk,      // System clock (e.g., 100MHz)
    input  wire             rst_n,        // Active low reset
    input  wire [WIDTH-1:0] tuning_word,  // Control input (sets frequency)
    output wire             dco_out       // Generated output clock
);

    // The Phase Accumulator
    reg [WIDTH-1:0] accumulator;

    always @(posedge sys_clk or negedge rst_n) begin
        if (!rst_n) begin
            accumulator <= {WIDTH{1'b0}};
        end else begin
            // Increment phase by the tuning word every cycle
            accumulator <= accumulator + tuning_word;
        end
    end

    // The MSB is the output clock (50% duty cycle on average, but with jitter)
    assign dco_out = accumulator[WIDTH-1];

endmodule

src/loop_filter.v
module loop_filter (
    input  wire              clk,
    input  wire              rst_n,
    input  wire              sample_en,
    input  wire signed [3:0] error_in,
    input  wire [4:0]        kp_shift,
    input  wire [4:0]        ki_shift,
    input  wire [31:0]       initial_freq,
    output reg  [31:0]       dco_ctrl,
    output reg               lock_detect
);

    reg signed [31:0] integrator;
    wire signed [31:0] prop_term;
    wire signed [31:0] integ_term;

    // 1. Sign Extension (Keep this from previous fix)
    assign prop_term  = $signed({{28{error_in[3]}}, error_in}) <<< kp_shift;
    assign integ_term = $signed({{28{error_in[3]}}, error_in}) <<< ki_shift;

    // 2. THE FIX: Calculate Next Integrator Combinatorially
    wire signed [31:0] next_integrator;
    assign next_integrator = integrator + integ_term;

    // Lock Detect Logic
    reg [4:0] zero_error_count;

    always @(posedge clk or negedge rst_n) begin
        if (!rst_n) begin
            integrator       <= initial_freq;
            dco_ctrl         <= initial_freq;
            zero_error_count <= 0;
            lock_detect      <= 0;
        end else if (sample_en) begin
            
            // Update Integrator with the pre-calculated value
            integrator <= next_integrator;

            // Use 'next_integrator' for output so we include immediate error
            dco_ctrl <= next_integrator + prop_term;

            // Lock Detection
            if (error_in == 0) begin
                if (zero_error_count < 20) 
                    zero_error_count <= zero_error_count + 1;
                else 
                    lock_detect <= 1'b1;
            end else begin
                zero_error_count <= 0;
                lock_detect <= 1'b0;
            end
        end
    end
endmodule

src/chain.v
module chain (
    input  wire              sys_clk,
    input  wire              rst_n,
    
    // Loop Filter Interface
    input  wire              sample_en,    // Pulse to update filter
    input  wire signed [3:0] error_in,     // "Push" command from PFD
    input  wire [4:0]        kp_shift,
    input  wire [4:0]        ki_shift,
    input  wire [31:0]       initial_freq, // Center Frequency
    
    // Divider Interface
    input  wire [31:0]       div_val,
    
    // Outputs
    output wire              dco_out,      // Fast Clock
    output wire              div_out,      // Slow Feedback Clock
    output wire              lock_detect
);

    // Internal Signal: Filter Output -> DCO Input
    wire [31:0] filter_to_dco_word;
    wire        dco_clk_internal;

    // 1. Loop Filter
    loop_filter lf_inst (
        .clk         (sys_clk),
        .rst_n       (rst_n),
        .sample_en   (sample_en),
        .error_in    (error_in),
        .kp_shift    (kp_shift),
        .ki_shift    (ki_shift),
        .initial_freq(initial_freq),
        .dco_ctrl    (filter_to_dco_word), // Drives the DCO
        .lock_detect (lock_detect)
    );

    // 2. DCO (NCO)
    dco_nco dco_inst (
        .sys_clk     (sys_clk),
        .rst_n       (rst_n),
        .tuning_word (filter_to_dco_word), // Driven by Filter
        .dco_out     (dco_clk_internal)
    );

    // 3. Divider
    divider div_inst (
        .clk_in      (dco_clk_internal),
        .rst_n       (rst_n),
        .div_val     (div_val),
        .clk_out     (div_out)
    );

    assign dco_out = dco_clk_internal;

endmodule

waveform_chain.vcd
$version Generated by VerilatedVcd $end
$timescale 1ps $end
 $scope module TOP $end
  $var wire 1 ' sys_clk $end
  $var wire 1 ( rst_n $end
  $var wire 1 ) sample_en $end
  $var wire 4 * error_in [3:0] $end
  $var wire 5 + kp_shift [4:0] $end
  $var wire 5 , ki_shift [4:0] $end
  $var wire 32 - initial_freq [31:0] $end
  $var wire 32 . div_val [31:0] $end
  $var wire 1 / dco_out $end
  $var wire 1 0 div_out $end
  $var wire 1 1 lock_detect $end
  $scope module chain $end
   $var wire 1 ' sys_clk $end
   $var wire 1 ( rst_n $end
   $var wire 1 ) sample_en $end
   $var wire 4 * error_in [3:0] $end
   $var wire 5 + kp_shift [4:0] $end
   $var wire 5 , ki_shift [4:0] $end
   $var wire 32 - initial_freq [31:0] $end
   $var wire 32 . div_val [31:0] $end
   $var wire 1 / dco_out $end
   $var wire 1 0 div_out $end
   $var wire 1 1 lock_detect $end
   $var wire 32 # filter_to_dco_word [31:0] $end
   $var wire 1 / dco_clk_internal $end
   $scope module dco_inst $end
    $var wire 32 6 WIDTH [31:0] $end
    $var wire 1 ' sys_clk $end
    $var wire 1 ( rst_n $end
    $var wire 32 # tuning_word [31:0] $end
    $var wire 1 / dco_out $end
    $var wire 32 $ accumulator [31:0] $end
   $upscope $end
   $scope module div_inst $end
    $var wire 1 / clk_in $end
    $var wire 1 ( rst_n $end
    $var wire 32 . div_val [31:0] $end
    $var wire 1 0 clk_out $end
    $var wire 32 2 counter [31:0] $end
   $upscope $end
   $scope module lf_inst $end
    $var wire 1 ' clk $end
    $var wire 1 ( rst_n $end
    $var wire 1 ) sample_en $end
    $var wire 4 * error_in [3:0] $end
    $var wire 5 + kp_shift [4:0] $end
    $var wire 5 , ki_shift [4:0] $end
    $var wire 32 - initial_freq [31:0] $end
    $var wire 32 # dco_ctrl [31:0] $end
    $var wire 1 1 lock_detect $end
    $var wire 32 % integrator [31:0] $end
    $var wire 32 3 prop_term [31:0] $end
    $var wire 32 4 integ_term [31:0] $end
    $var wire 32 5 next_integrator [31:0] $end
    $var wire 5 & zero_error_count [4:0] $end
   $upscope $end
  $upscope $end
 $upscope $end
$enddefinitions $end


#0
b00000000000000000000000000000000 #
b00000000000000000000000000000000 $
b00000000000000000000000000000000 %
b00000 &
1'
1(
0)
b0000 *
b10110 +
b10010 ,
b00011001100110011001100110011010 -
b00000000000000000000000000000100 .
0/
00
01
b00000000000000000000000000000000 2
b00000000000000000000000000000000 3
b00000000000000000000000000000000 4
b00000000000000000000000000000000 5
b00000000000000000000000000100000 6
#1
0'
#2
b00011001100110011001100110011010 #
b00011001100110011001100110011010 %
1'
0(
b00011001100110011001100110011010 5
#3
0'
#4
1'
#5
0'
#6
b00011001100110011001100110011010 $
1'
1(
#7
0'
#8
b00110011001100110011001100110100 $
1'
#9
0'
#10
b01001100110011001100110011001110 $
1'
#11
0'
#12
b01100110011001100110011001101000 $
1'
#13
0'
#14
b10000000000000000000000000000010 $
1'
1/
10
b00000000000000000000000000000001 2
#15
0'
#16
b10011001100110011001100110011100 $
1'
#17
0'
#18
b10110011001100110011001100110110 $
1'
#19
0'
#20
b11001100110011001100110011010000 $
1'
#21
0'
#22
b11100110011001100110011001101010 $
1'
#23
0'
#24
b00000000000000000000000000000100 $
1'
0/
#25
0'
#26
b00011001100110011001100110011110 $
1'
#27
0'
#28
b00110011001100110011001100111000 $
1'
#29
0'
#30
b01001100110011001100110011010010 $
1'
#31
0'
#32
b01100110011001100110011001101100 $
1'
#33
0'
#34
b10000000000000000000000000000110 $
1'
1/
00
b00000000000000000000000000000010 2
#35
0'
#36
b10011001100110011001100110100000 $
1'
#37
0'
#38
b10110011001100110011001100111010 $
1'
#39
0'
#40
b11001100110011001100110011010100 $
1'
#41
0'
#42
b11100110011001100110011001101110 $
1'
#43
0'
#44
b00000000000000000000000000001000 $
1'
0/
#45
0'
#46
b00011001100110011001100110100010 $
1'
#47
0'
#48
b00110011001100110011001100111100 $
1'
#49
0'
#50
b01001100110011001100110011010110 $
1'
#51
0'
#52
b01100110011001100110011001110000 $
1'
#53
0'
#54
b10000000000000000000000000001010 $
1'
1/
b00000000000000000000000000000011 2
#55
0'
#56
b10011001100110011001100110100100 $
1'
#57
0'
#58
b10110011001100110011001100111110 $
1'
#59
0'
#60
b11001100110011001100110011011000 $
1'
#61
0'
#62
b11100110011001100110011001110010 $
1'
#63
0'
#64
b00000000000000000000000000001100 $
1'
0/
#65
0'
#66
b00011001100110011001100110100110 $
1'
#67
0'
#68
b00110011001100110011001101000000 $
1'
#69
0'
#70
b01001100110011001100110011011010 $
1'
#71
0'
#72
b01100110011001100110011001110100 $
1'
#73
0'
#74
b10000000000000000000000000001110 $
1'
1/
10
b00000000000000000000000000000000 2
#75
0'
#76
b10011001100110011001100110101000 $
1'
#77
0'
#78
b10110011001100110011001101000010 $
1'
#79
0'
#80
b11001100110011001100110011011100 $
1'
#81
0'
#82
b11100110011001100110011001110110 $
1'
#83
0'
#84
b00000000000000000000000000010000 $
1'
0/
#85
0'
#86
b00011001100110011001100110101010 $
1'
#87
0'
#88
b00110011001100110011001101000100 $
1'
#89
0'
#90
b01001100110011001100110011011110 $
1'
#91
0'
#92
b01100110011001100110011001111000 $
1'
#93
0'
#94
b10000000000000000000000000010010 $
1'
1/
b00000000000000000000000000000001 2
#95
0'
#96
b10011001100110011001100110101100 $
1'
#97
0'
#98
b10110011001100110011001101000110 $
1'
#99
0'
#100
b11001100110011001100110011100000 $
1'
#101
0'
#102
b11100110011001100110011001111010 $
1'
#103
0'
#104
b00000000000000000000000000010100 $
1'
0/
#105
0'
#106
b00011001100110011001100110101110 $
1'
#107
0'
#108
b00110011001100110011001101001000 $
1'
#109
0'
#110
b01001100110011001100110011100010 $
1'
#111
0'
#112
b01100110011001100110011001111100 $
1'
#113
0'
#114
b10000000000000000000000000010110 $
1'
1/
00
b00000000000000000000000000000010 2
#115
0'
#116
b10011001100110011001100110110000 $
1'
#117
0'
#118
b10110011001100110011001101001010 $
1'
#119
0'
#120
b11001100110011001100110011100100 $
1'
#121
0'
#122
b11100110011001100110011001111110 $
1'
#123
0'
#124
b00000000000000000000000000011000 $
1'
0/
#125
0'
#126
b00011001100110011001100110110010 $
1'
#127
0'
#128
b00110011001100110011001101001100 $
1'
#129
0'
#130
b01001100110011001100110011100110 $
1'
#131
0'
#132
b01100110011001100110011010000000 $
1'
#133
0'
#134
b10000000000000000000000000011010 $
1'
1/
b00000000000000000000000000000011 2
#135
0'
#136
b10011001100110011001100110110100 $
1'
#137
0'
#138
b10110011001100110011001101001110 $
1'
#139
0'
#140
b11001100110011001100110011101000 $
1'
#141
0'
#142
b11100110011001100110011010000010 $
1'
#143
0'
#144
b00000000000000000000000000011100 $
1'
0/
#145
0'
#146
b00011001100110011001100110110110 $
1'
#147
0'
#148
b00110011001100110011001101010000 $
1'
#149
0'
#150
b01001100110011001100110011101010 $
1'
#151
0'
#152
b01100110011001100110011010000100 $
1'
#153
0'
#154
b10000000000000000000000000011110 $
1'
1/
10
b00000000000000000000000000000000 2
#155
0'
#156
b10011001100110011001100110111000 $
1'
#157
0'
#158
b10110011001100110011001101010010 $
1'
#159
0'
#160
b11001100110011001100110011101100 $
1'
#161
0'
#162
b11100110011001100110011010000110 $
1'
#163
0'
#164
b00000000000000000000000000100000 $
1'
0/
#165
0'
#166
b00011001100110011001100110111010 $
1'
#167
0'
#168
b00110011001100110011001101010100 $
1'
#169
0'
#170
b01001100110011001100110011101110 $
1'
#171
0'
#172
b01100110011001100110011010001000 $
1'
#173
0'
#174
b10000000000000000000000000100010 $
1'
1/
b00000000000000000000000000000001 2
#175
0'
#176
b10011001100110011001100110111100 $
1'
#177
0'
#178
b10110011001100110011001101010110 $
1'
#179
0'
#180
b11001100110011001100110011110000 $
1'
#181
0'
#182
b11100110011001100110011010001010 $
1'
#183
0'
#184
b00000000000000000000000000100100 $
1'
0/
#185
0'
#186
b00011001100110011001100110111110 $
1'
#187
0'
#188
b00110011001100110011001101011000 $
1'
#189
0'
#190
b01001100110011001100110011110010 $
1'
#191
0'
#192
b01100110011001100110011010001100 $
1'
#193
0'
#194
b10000000000000000000000000100110 $
1'
1/
00
b00000000000000000000000000000010 2
#195
0'
#196
b10011001100110011001100111000000 $
1'
#197
0'
#198
b10110011001100110011001101011010 $
1'
#199
0'
#200
b11001100110011001100110011110100 $
1'
#201
0'
#202
b11100110011001100110011010001110 $
1'
#203
0'
#204
b00000000000000000000000000101000 $
1'
0/
#205
0'
#206
b00011001100110011001100111000010 $
1'
#207
0'
#208
b00110011001100110011001101011100 $
1'
#209
0'
#210
b01001100110011001100110011110110 $
1'
#211
0'
#212
b01100110011001100110011010010000 $
1'
#213
0'
#214
b10000000000000000000000000101010 $
1'
1/
b00000000000000000000000000000011 2
#215
0'
#216
b10011001100110011001100111000100 $
1'
#217
0'
#218
b10110011001100110011001101011110 $
1'
#219
0'
#220
b11001100110011001100110011111000 $
1'
#221
0'
#222
b11100110011001100110011010010010 $
1'
#223
0'
#224
b00000000000000000000000000101100 $
1'
0/
#225
0'
#226
b00011001100110011001100111000110 $
1'
#227
0'
#228
b00110011001100110011001101100000 $
1'
#229
0'
#230
b01001100110011001100110011111010 $
1'
#231
0'
#232
b01100110011001100110011010010100 $
1'
#233
0'
#234
b10000000000000000000000000101110 $
1'
1/
10
b00000000000000000000000000000000 2
#235
0'
#236
b10011001100110011001100111001000 $
1'
#237
0'
#238
b10110011001100110011001101100010 $
1'
#239
0'
#240
b11001100110011001100110011111100 $
1'
#241
0'
#242
b11100110011001100110011010010110 $
1'
#243
0'
#244
b00000000000000000000000000110000 $
1'
0/
#245
0'
#246
b00011001100110011001100111001010 $
1'
#247
0'
#248
b00110011001100110011001101100100 $
1'
#249
0'
#250
b01001100110011001100110011111110 $
1'
#251
0'
#252
b01100110011001100110011010011000 $
1'
#253
0'
#254
b10000000000000000000000000110010 $
1'
1/
b00000000000000000000000000000001 2
#255
0'
#256
b10011001100110011001100111001100 $
1'
#257
0'
#258
b10110011001100110011001101100110 $
1'
#259
0'
#260
b11001100110011001100110100000000 $
1'
#261
0'
#262
b11100110011001100110011010011010 $
1'
#263
0'
#264
b00000000000000000000000000110100 $
1'
0/
#265
0'
#266
b00011001100110011001100111001110 $
1'
#267
0'
#268
b00110011001100110011001101101000 $
1'
#269
0'
#270
b01001100110011001100110100000010 $
1'
#271
0'
#272
b01100110011001100110011010011100 $
1'
#273
0'
#274
b10000000000000000000000000110110 $
1'
1/
00
b00000000000000000000000000000010 2
#275
0'
#276
b10011001100110011001100111010000 $
1'
#277
0'
#278
b10110011001100110011001101101010 $
1'
#279
0'
#280
b11001100110011001100110100000100 $
1'
#281
0'
#282
b11100110011001100110011010011110 $
1'
#283
0'
#284
b00000000000000000000000000111000 $
1'
0/
#285
0'
#286
b00011001100110011001100111010010 $
1'
#287
0'
#288
b00110011001100110011001101101100 $
1'
#289
0'
#290
b01001100110011001100110100000110 $
1'
#291
0'
#292
b01100110011001100110011010100000 $
1'
#293
0'
#294
b10000000000000000000000000111010 $
1'
1/
b00000000000000000000000000000011 2
#295
0'
#296
b10011001100110011001100111010100 $
1'
#297
0'
#298
b10110011001100110011001101101110 $
1'
#299
0'
#300
b11001100110011001100110100001000 $
1'
#301
0'
#302
b11100110011001100110011010100010 $
1'
#303
0'
#304
b00000000000000000000000000111100 $
1'
0/
#305
0'
#306
b00011001100110011001100111010110 $
1'
#307
0'
#308
b00110011001100110011001101110000 $
1'
#309
0'
#310
b01001100110011001100110100001010 $
1'
#311
0'
#312
b01100110011001100110011010100100 $
1'
#313
0'
#314
b10000000000000000000000000111110 $
1'
1/
10
b00000000000000000000000000000000 2
#315
0'
#316
b10011001100110011001100111011000 $
1'
#317
0'
#318
b10110011001100110011001101110010 $
1'
#319
0'
#320
b11001100110011001100110100001100 $
1'
#321
0'
#322
b11100110011001100110011010100110 $
1'
#323
0'
#324
b00000000000000000000000001000000 $
1'
0/
#325
0'
#326
b00011001100110011001100111011010 $
1'
#327
0'
#328
b00110011001100110011001101110100 $
1'
#329
0'
#330
b01001100110011001100110100001110 $
1'
#331
0'
#332
b01100110011001100110011010101000 $
1'
#333
0'
#334
b10000000000000000000000001000010 $
1'
1/
b00000000000000000000000000000001 2
#335
0'
#336
b10011001100110011001100111011100 $
1'
#337
0'
#338
b10110011001100110011001101110110 $
1'
#339
0'
#340
b11001100110011001100110100010000 $
1'
#341
0'
#342
b11100110011001100110011010101010 $
1'
#343
0'
#344
b00000000000000000000000001000100 $
1'
0/
#345
0'
#346
b00011001100110011001100111011110 $
1'
#347
0'
#348
b00110011001100110011001101111000 $
1'
#349
0'
#350
b01001100110011001100110100010010 $
1'
#351
0'
#352
b01100110011001100110011010101100 $
1'
#353
0'
#354
b10000000000000000000000001000110 $
1'
1/
00
b00000000000000000000000000000010 2
#355
0'
#356
b10011001100110011001100111100000 $
1'
#357
0'
#358
b10110011001100110011001101111010 $
1'
#359
0'
#360
b11001100110011001100110100010100 $
1'
#361
0'
#362
b11100110011001100110011010101110 $
1'
#363
0'
#364
b00000000000000000000000001001000 $
1'
0/
#365
0'
#366
b00011001100110011001100111100010 $
1'
#367
0'
#368
b00110011001100110011001101111100 $
1'
#369
0'
#370
b01001100110011001100110100010110 $
1'
#371
0'
#372
b01100110011001100110011010110000 $
1'
#373
0'
#374
b10000000000000000000000001001010 $
1'
1/
b00000000000000000000000000000011 2
#375
0'
#376
b10011001100110011001100111100100 $
1'
#377
0'
#378
b10110011001100110011001101111110 $
1'
#379
0'
#380
b11001100110011001100110100011000 $
1'
#381
0'
#382
b11100110011001100110011010110010 $
1'
#383
0'
#384
b00000000000000000000000001001100 $
1'
0/
#385
0'
#386
b00011001100110011001100111100110 $
1'
#387
0'
#388
b00110011001100110011001110000000 $
1'
#389
0'
#390
b01001100110011001100110100011010 $
1'
#391
0'
#392
b01100110011001100110011010110100 $
1'
#393
0'
#394
b10000000000000000000000001001110 $
1'
1/
10
b00000000000000000000000000000000 2
#395
0'
#396
b10011001100110011001100111101000 $
1'
#397
0'
#398
b10110011001100110011001110000010 $
1'
#399
0'
#400
b11001100110011001100110100011100 $
1'
#401
0'
#402
b11100110011001100110011010110110 $
1'
#403
0'
#404
b00000000000000000000000001010000 $
1'
0/
#405
0'
#406
b00011001100110011001100111101010 $
1'
#407
0'
#408
b00110011001100110011001110000100 $
1'
#409
0'
#410
b01001100110011001100110100011110 $
1'
#411
0'
#412
b01100110011001100110011010111000 $
1'
#413
0'
#414
b10000000000000000000000001010010 $
1'
1/
b00000000000000000000000000000001 2
#415
0'
#416
b10011001100110011001100111101100 $
1'
#417
0'
#418
b10110011001100110011001110000110 $
1'
#419
0'
#420
b11001100110011001100110100100000 $
1'
#421
0'
#422
b11100110011001100110011010111010 $
1'
#423
0'
#424
b00000000000000000000000001010100 $
1'
0/
#425
0'
#426
b00011001100110011001100111101110 $
1'
#427
0'
#428
b00110011001100110011001110001000 $
1'
#429
0'
#430
b01001100110011001100110100100010 $
1'
#431
0'
#432
b01100110011001100110011010111100 $
1'
#433
0'
#434
b10000000000000000000000001010110 $
1'
1/
00
b00000000000000000000000000000010 2
#435
0'
#436
b10011001100110011001100111110000 $
1'
#437
0'
#438
b10110011001100110011001110001010 $
1'
#439
0'
#440
b11001100110011001100110100100100 $
1'
#441
0'
#442
b11100110011001100110011010111110 $
1'
#443
0'
#444
b00000000000000000000000001011000 $
1'
0/
#445
0'
#446
b00011001100110011001100111110010 $
1'
#447
0'
#448
b00110011001100110011001110001100 $
1'
#449
0'
#450
b01001100110011001100110100100110 $
1'
#451
0'
#452
b01100110011001100110011011000000 $
1'
#453
0'
#454
b10000000000000000000000001011010 $
1'
1/
b00000000000000000000000000000011 2
#455
0'
#456
b10011001100110011001100111110100 $
1'
#457
0'
#458
b10110011001100110011001110001110 $
1'
#459
0'
#460
b11001100110011001100110100101000 $
1'
#461
0'
#462
b11100110011001100110011011000010 $
1'
#463
0'
#464
b00000000000000000000000001011100 $
1'
0/
#465
0'
#466
b00011001100110011001100111110110 $
1'
#467
0'
#468
b00110011001100110011001110010000 $
1'
#469
0'
#470
b01001100110011001100110100101010 $
1'
#471
0'
#472
b01100110011001100110011011000100 $
1'
#473
0'
#474
b10000000000000000000000001011110 $
1'
1/
10
b00000000000000000000000000000000 2
#475
0'
#476
b10011001100110011001100111111000 $
1'
#477
0'
#478
b10110011001100110011001110010010 $
1'
#479
0'
#480
b11001100110011001100110100101100 $
1'
#481
0'
#482
b11100110011001100110011011000110 $
1'
#483
0'
#484
b00000000000000000000000001100000 $
1'
0/
#485
0'
#486
b00011001100110011001100111111010 $
1'
#487
0'
#488
b00110011001100110011001110010100 $
1'
#489
0'
#490
b01001100110011001100110100101110 $
1'
#491
0'
#492
b01100110011001100110011011001000 $
1'
#493
0'
#494
b10000000000000000000000001100010 $
1'
1/
b00000000000000000000000000000001 2
#495
0'
#496
b10011001100110011001100111111100 $
1'
#497
0'
#498
b10110011001100110011001110010110 $
1'
#499
0'
#500
b11001100110011001100110100110000 $
1'
#501
0'
#502
b11100110011001100110011011001010 $
1'
#503
0'
#504
b00000000000000000000000001100100 $
1'
0/
#505
0'
#506
b00011001100110011001100111111110 $
1'
#507
0'
#508
b00110011001100110011001110011000 $
1'
#509
0'
#510
b01001100110011001100110100110010 $
1'
#511
0'
#512
b01100110011001100110011011001100 $
1'
#513
0'
#514
b10000000000000000000000001100110 $
1'
1/
00
b00000000000000000000000000000010 2
#515
0'
#516
b10011001100110011001101000000000 $
1'
#517
0'
#518
b10110011001100110011001110011010 $
1'
#519
0'
#520
b11001100110011001100110100110100 $
1'
#521
0'
#522
b11100110011001100110011011001110 $
1'
#523
0'
#524
b00000000000000000000000001101000 $
1'
0/
#525
0'
#526
b00011001100110011001101000000010 $
1'
#527
0'
#528
b00110011001100110011001110011100 $
1'
#529
0'
#530
b01001100110011001100110100110110 $
1'
#531
0'
#532
b01100110011001100110011011010000 $
1'
#533
0'
#534
b10000000000000000000000001101010 $
1'
1/
b00000000000000000000000000000011 2
#535
0'
#536
b10011001100110011001101000000100 $
1'
#537
0'
#538
b10110011001100110011001110011110 $
1'
#539
0'
#540
b11001100110011001100110100111000 $
1'
#541
0'
#542
b11100110011001100110011011010010 $
1'
#543
0'
#544
b00000000000000000000000001101100 $
1'
0/
#545
0'
#546
b00011001100110011001101000000110 $
1'
#547
0'
#548
b00110011001100110011001110100000 $
1'
#549
0'
#550
b01001100110011001100110100111010 $
1'
#551
0'
#552
b01100110011001100110011011010100 $
1'
#553
0'
#554
b10000000000000000000000001101110 $
1'
1/
10
b00000000000000000000000000000000 2
#555
0'
#556
b10011001100110011001101000001000 $
1'
#557
0'
#558
b10110011001100110011001110100010 $
1'
#559
0'
#560
b11001100110011001100110100111100 $
1'
#561
0'
#562
b11100110011001100110011011010110 $
1'
#563
0'
#564
b00000000000000000000000001110000 $
1'
0/
#565
0'
#566
b00011001100110011001101000001010 $
1'
#567
0'
#568
b00110011001100110011001110100100 $
1'
#569
0'
#570
b01001100110011001100110100111110 $
1'
#571
0'
#572
b01100110011001100110011011011000 $
1'
#573
0'
#574
b10000000000000000000000001110010 $
1'
1/
b00000000000000000000000000000001 2
#575
0'
#576
b10011001100110011001101000001100 $
1'
#577
0'
#578
b10110011001100110011001110100110 $
1'
#579
0'
#580
b11001100110011001100110101000000 $
1'
#581
0'
#582
b11100110011001100110011011011010 $
1'
#583
0'
#584
b00000000000000000000000001110100 $
1'
0/
#585
0'
#586
b00011001100110011001101000001110 $
1'
#587
0'
#588
b00110011001100110011001110101000 $
1'
#589
0'
#590
b01001100110011001100110101000010 $
1'
#591
0'
#592
b01100110011001100110011011011100 $
1'
#593
0'
#594
b10000000000000000000000001110110 $
1'
1/
00
b00000000000000000000000000000010 2
#595
0'
#596
b10011001100110011001101000010000 $
1'
#597
0'
#598
b10110011001100110011001110101010 $
1'
#599
0'
#600
b11001100110011001100110101000100 $
1'
#601
0'
#602
b11100110011001100110011011011110 $
1'
#603
0'
#604
b00000000000000000000000001111000 $
1'
0/
#605
0'
#606
b00011001100110011001101000010010 $
1'
#607
0'
#608
b00110011001100110011001110101100 $
1'
#609
0'
#610
b01001100110011001100110101000110 $
1'
#611
0'
#612
b01100110011001100110011011100000 $
1'
#613
0'
#614
b10000000000000000000000001111010 $
1'
1/
b00000000000000000000000000000011 2
#615
0'
#616
b10011001100110011001101000010100 $
1'
#617
0'
#618
b10110011001100110011001110101110 $
1'
#619
0'
#620
b11001100110011001100110101001000 $
1'
#621
0'
#622
b11100110011001100110011011100010 $
1'
#623
0'
#624
b00000000000000000000000001111100 $
1'
0/
#625
0'
#626
b00011001100110011001101000010110 $
1'
#627
0'
#628
b00110011001100110011001110110000 $
1'
#629
0'
#630
b01001100110011001100110101001010 $
1'
#631
0'
#632
b01100110011001100110011011100100 $
1'
#633
0'
#634
b10000000000000000000000001111110 $
1'
1/
10
b00000000000000000000000000000000 2
#635
0'
#636
b10011001100110011001101000011000 $
1'
#637
0'
#638
b10110011001100110011001110110010 $
1'
#639
0'
#640
b11001100110011001100110101001100 $
1'
#641
0'
#642
b11100110011001100110011011100110 $
1'
#643
0'
#644
b00000000000000000000000010000000 $
1'
0/
#645
0'
#646
b00011001100110011001101000011010 $
1'
#647
0'
#648
b00110011001100110011001110110100 $
1'
#649
0'
#650
b01001100110011001100110101001110 $
1'
#651
0'
#652
b01100110011001100110011011101000 $
1'
#653
0'
#654
b10000000000000000000000010000010 $
1'
1/
b00000000000000000000000000000001 2
#655
0'
#656
b10011001100110011001101000011100 $
1'
#657
0'
#658
b10110011001100110011001110110110 $
1'
#659
0'
#660
b11001100110011001100110101010000 $
1'
#661
0'
#662
b11100110011001100110011011101010 $
1'
#663
0'
#664
b00000000000000000000000010000100 $
1'
0/
#665
0'
#666
b00011001100110011001101000011110 $
1'
#667
0'
#668
b00110011001100110011001110111000 $
1'
#669
0'
#670
b01001100110011001100110101010010 $
1'
#671
0'
#672
b01100110011001100110011011101100 $
1'
#673
0'
#674
b10000000000000000000000010000110 $
1'
1/
00
b00000000000000000000000000000010 2
#675
0'
#676
b10011001100110011001101000100000 $
1'
#677
0'
#678
b10110011001100110011001110111010 $
1'
#679
0'
#680
b11001100110011001100110101010100 $
1'
#681
0'
#682
b11100110011001100110011011101110 $
1'
#683
0'
#684
b00000000000000000000000010001000 $
1'
0/
#685
0'
#686
b00011001100110011001101000100010 $
1'
#687
0'
#688
b00110011001100110011001110111100 $
1'
#689
0'
#690
b01001100110011001100110101010110 $
1'
#691
0'
#692
b01100110011001100110011011110000 $
1'
#693
0'
#694
b10000000000000000000000010001010 $
1'
1/
b00000000000000000000000000000011 2
#695
0'
#696
b10011001100110011001101000100100 $
1'
#697
0'
#698
b10110011001100110011001110111110 $
1'
#699
0'
#700
b11001100110011001100110101011000 $
1'
#701
0'
#702
b11100110011001100110011011110010 $
1'
#703
0'
#704
b00000000000000000000000010001100 $
1'
0/
#705
0'
#706
b00011001100110011001101000100110 $
1'
#707
0'
#708
b00110011001100110011001111000000 $
1'
#709
0'
#710
b01001100110011001100110101011010 $
1'
#711
0'
#712
b01100110011001100110011011110100 $
1'
#713
0'
#714
b10000000000000000000000010001110 $
1'
1/
10
b00000000000000000000000000000000 2
#715
0'
#716
b10011001100110011001101000101000 $
1'
#717
0'
#718
b10110011001100110011001111000010 $
1'
#719
0'
#720
b11001100110011001100110101011100 $
1'
#721
0'
#722
b11100110011001100110011011110110 $
1'
#723
0'
#724
b00000000000000000000000010010000 $
1'
0/
#725
0'
#726
b00011001100110011001101000101010 $
1'
#727
0'
#728
b00110011001100110011001111000100 $
1'
#729
0'
#730
b01001100110011001100110101011110 $
1'
#731
0'
#732
b01100110011001100110011011111000 $
1'
#733
0'
#734
b10000000000000000000000010010010 $
1'
1/
b00000000000000000000000000000001 2
#735
0'
#736
b10011001100110011001101000101100 $
1'
#737
0'
#738
b10110011001100110011001111000110 $
1'
#739
0'
#740
b11001100110011001100110101100000 $
1'
#741
0'
#742
b11100110011001100110011011111010 $
1'
#743
0'
#744
b00000000000000000000000010010100 $
1'
0/
#745
0'
#746
b00011001100110011001101000101110 $
1'
#747
0'
#748
b00110011001100110011001111001000 $
1'
#749
0'
#750
b01001100110011001100110101100010 $
1'
#751
0'
#752
b01100110011001100110011011111100 $
1'
#753
0'
#754
b10000000000000000000000010010110 $
1'
1/
00
b00000000000000000000000000000010 2
#755
0'
#756
b10011001100110011001101000110000 $
1'
#757
0'
#758
b10110011001100110011001111001010 $
1'
#759
0'
#760
b11001100110011001100110101100100 $
1'
#761
0'
#762
b11100110011001100110011011111110 $
1'
#763
0'
#764
b00000000000000000000000010011000 $
1'
0/
#765
0'
#766
b00011001100110011001101000110010 $
1'
#767
0'
#768
b00110011001100110011001111001100 $
1'
#769
0'
#770
b01001100110011001100110101100110 $
1'
#771
0'
#772
b01100110011001100110011100000000 $
1'
#773
0'
#774
b10000000000000000000000010011010 $
1'
1/
b00000000000000000000000000000011 2
#775
0'
#776
b10011001100110011001101000110100 $
1'
#777
0'
#778
b10110011001100110011001111001110 $
1'
#779
0'
#780
b11001100110011001100110101101000 $
1'
#781
0'
#782
b11100110011001100110011100000010 $
1'
#783
0'
#784
b00000000000000000000000010011100 $
1'
0/
#785
0'
#786
b00011001100110011001101000110110 $
1'
#787
0'
#788
b00110011001100110011001111010000 $
1'
#789
0'
#790
b01001100110011001100110101101010 $
1'
#791
0'
#792
b01100110011001100110011100000100 $
1'
#793
0'
