src/dco_nco.v
module dco_nco #(
    parameter WIDTH = 32  // Accumulator width. Higher = finer frequency resolution
)(
    input  wire             sys_clk,      // System clock (e.g., 100MHz)
    input  wire             rst_n,        // Active low reset
    input  wire [WIDTH-1:0] tuning_word,  // Control input (sets frequency)
    output wire             dco_out       // Generated output clock
);

    // The Phase Accumulator
    reg [WIDTH-1:0] accumulator;

    always @(posedge sys_clk or negedge rst_n) begin
        if (!rst_n) begin
            accumulator <= {WIDTH{1'b0}};
        end else begin
            // Increment phase by the tuning word every cycle
            accumulator <= accumulator + tuning_word;
        end
    end

    // The MSB is the output clock (50% duty cycle on average, but with jitter)
    assign dco_out = accumulator[WIDTH-1];
endmodule

waveform.vcd
$version Generated by VerilatedVcd $end
$timescale 1ps $end
 $scope module TOP $end
  $var wire 1 # sys_clk $end
  $var wire 1 $ rst_n $end
  $var wire 32 % tuning_word [31:0] $end
  $var wire 1 & dco_out $end
  $scope module dco_nco $end
   $var wire 32 ( WIDTH [31:0] $end
   $var wire 1 # sys_clk $end
   $var wire 1 $ rst_n $end
   $var wire 32 % tuning_word [31:0] $end
   $var wire 1 & dco_out $end
   $var wire 32 ' accumulator [31:0] $end
  $upscope $end
 $upscope $end
$enddefinitions $end


#0
1#
0$
b00001100110011001100110011001101 %
0&
b00000000000000000000000000000000 '
b00000000000000000000000000100000 (
#1
0#
#2
1#
#3
0#
#4
1#
#5
0#
#6
1#
#7
0#
#8
1#
#9
0#
#10
1#
#11
0#
#12
1#
#13
0#
#14
1#
#15
0#
#16
1#
#17
0#
#18
1#
#19
0#
#20
1#
#21
0#
1$
#22
1#
b00001100110011001100110011001101 '
#23
0#
#24
1#
b00011001100110011001100110011010 '
#25
0#
#26
1#
b00100110011001100110011001100111 '
#27
0#
#28
1#
b00110011001100110011001100110100 '
#29
0#
#30
1#
b01000000000000000000000000000001 '
#31
0#
#32
1#
b01001100110011001100110011001110 '
#33
0#
#34
1#
b01011001100110011001100110011011 '
#35
0#
#36
1#
b01100110011001100110011001101000 '
#37
0#
#38
1#
b01110011001100110011001100110101 '
#39
0#
#40
1#
1&
b10000000000000000000000000000010 '
#41
0#
#42
1#
b10001100110011001100110011001111 '
#43
0#
#44
1#
b10011001100110011001100110011100 '
#45
0#
#46
1#
b10100110011001100110011001101001 '
#47
0#
#48
1#
b10110011001100110011001100110110 '
#49
0#
#50
1#
b11000000000000000000000000000011 '
#51
0#
#52
1#
b11001100110011001100110011010000 '
#53
0#
#54
1#
b11011001100110011001100110011101 '
#55
0#
#56
1#
b11100110011001100110011001101010 '
#57
0#
#58
1#
b11110011001100110011001100110111 '
#59
0#
#60
1#
0&
b00000000000000000000000000000100 '
#61
0#
#62
1#
b00001100110011001100110011010001 '
#63
0#
#64
1#
b00011001100110011001100110011110 '
#65
0#
#66
1#
b00100110011001100110011001101011 '
#67
0#
#68
1#
b00110011001100110011001100111000 '
#69
0#
#70
1#
b01000000000000000000000000000101 '
#71
0#
#72
1#
b01001100110011001100110011010010 '
#73
0#
#74
1#
b01011001100110011001100110011111 '
#75
0#
#76
1#
b01100110011001100110011001101100 '
#77
0#
#78
1#
b01110011001100110011001100111001 '
#79
0#
#80
1#
1&
b10000000000000000000000000000110 '
#81
0#
#82
1#
b10001100110011001100110011010011 '
#83
0#
#84
1#
b10011001100110011001100110100000 '
#85
0#
#86
1#
b10100110011001100110011001101101 '
#87
0#
#88
1#
b10110011001100110011001100111010 '
#89
0#
#90
1#
b11000000000000000000000000000111 '
#91
0#
#92
1#
b11001100110011001100110011010100 '
#93
0#
#94
1#
b11011001100110011001100110100001 '
#95
0#
#96
1#
b11100110011001100110011001101110 '
#97
0#
#98
1#
b11110011001100110011001100111011 '
#99
0#
#100
1#
0&
b00000000000000000000000000001000 '
#101
0#
#102
1#
b00001100110011001100110011010101 '
#103
0#
#104
1#
b00011001100110011001100110100010 '
#105
0#
#106
1#
b00100110011001100110011001101111 '
#107
0#
#108
1#
b00110011001100110011001100111100 '
#109
0#
#110
1#
b01000000000000000000000000001001 '
#111
0#
#112
1#
b01001100110011001100110011010110 '
#113
0#
#114
1#
b01011001100110011001100110100011 '
#115
0#
#116
1#
b01100110011001100110011001110000 '
#117
0#
#118
1#
b01110011001100110011001100111101 '
#119
0#
#120
1#
1&
b10000000000000000000000000001010 '
#121
0#
#122
1#
b10001100110011001100110011010111 '
#123
0#
#124
1#
b10011001100110011001100110100100 '
#125
0#
#126
1#
b10100110011001100110011001110001 '
#127
0#
#128
1#
b10110011001100110011001100111110 '
#129
0#
#130
1#
b11000000000000000000000000001011 '
#131
0#
#132
1#
b11001100110011001100110011011000 '
#133
0#
#134
1#
b11011001100110011001100110100101 '
#135
0#
#136
1#
b11100110011001100110011001110010 '
#137
0#
#138
1#
b11110011001100110011001100111111 '
#139
0#
#140
1#
0&
b00000000000000000000000000001100 '
#141
0#
#142
1#
b00001100110011001100110011011001 '
#143
0#
#144
1#
b00011001100110011001100110100110 '
#145
0#
#146
1#
b00100110011001100110011001110011 '
#147
0#
#148
1#
b00110011001100110011001101000000 '
#149
0#
#150
1#
b01000000000000000000000000001101 '
#151
0#
#152
1#
b01001100110011001100110011011010 '
#153
0#
#154
1#
b01011001100110011001100110100111 '
#155
0#
#156
1#
b01100110011001100110011001110100 '
#157
0#
#158
1#
b01110011001100110011001101000001 '
#159
0#
#160
1#
1&
b10000000000000000000000000001110 '
#161
0#
b00011001100110011001100110011010 %
#162
1#
b10011001100110011001100110101000 '
#163
0#
#164
1#
b10110011001100110011001101000010 '
#165
0#
#166
1#
b11001100110011001100110011011100 '
#167
0#
#168
1#
b11100110011001100110011001110110 '
#169
0#
#170
1#
0&
b00000000000000000000000000010000 '
#171
0#
#172
1#
b00011001100110011001100110101010 '
#173
0#
#174
1#
b00110011001100110011001101000100 '
#175
0#
#176
1#
b01001100110011001100110011011110 '
#177
0#
#178
1#
b01100110011001100110011001111000 '
#179
0#
#180
1#
1&
b10000000000000000000000000010010 '
#181
0#
#182
1#
b10011001100110011001100110101100 '
#183
0#
#184
1#
b10110011001100110011001101000110 '
#185
0#
#186
1#
b11001100110011001100110011100000 '
#187
0#
#188
1#
b11100110011001100110011001111010 '
#189
0#
#190
1#
0&
b00000000000000000000000000010100 '
#191
0#
#192
1#
b00011001100110011001100110101110 '
#193
0#
#194
1#
b00110011001100110011001101001000 '
#195
0#
#196
1#
b01001100110011001100110011100010 '
#197
0#
#198
1#
b01100110011001100110011001111100 '
#199
0#
#200
1#
1&
b10000000000000000000000000010110 '
#201
0#
#202
1#
b10011001100110011001100110110000 '
#203
0#
#204
1#
b10110011001100110011001101001010 '
#205
0#
#206
1#
b11001100110011001100110011100100 '
#207
0#
#208
1#
b11100110011001100110011001111110 '
#209
0#
#210
1#
0&
b00000000000000000000000000011000 '
#211
0#
#212
1#
b00011001100110011001100110110010 '
#213
0#
#214
1#
b00110011001100110011001101001100 '
#215
0#
#216
1#
b01001100110011001100110011100110 '
#217
0#
#218
1#
b01100110011001100110011010000000 '
#219
0#
#220
1#
1&
b10000000000000000000000000011010 '
#221
0#
#222
1#
b10011001100110011001100110110100 '
#223
0#
#224
1#
b10110011001100110011001101001110 '
#225
0#
#226
1#
b11001100110011001100110011101000 '
#227
0#
#228
1#
b11100110011001100110011010000010 '
#229
0#
#230
1#
0&
b00000000000000000000000000011100 '
#231
0#
#232
1#
b00011001100110011001100110110110 '
#233
0#
#234
1#
b00110011001100110011001101010000 '
#235
0#
#236
1#
b01001100110011001100110011101010 '
#237
0#
#238
1#
b01100110011001100110011010000100 '
#239
0#
#240
1#
1&
b10000000000000000000000000011110 '
#241
0#
b01000000000000000000000000000000 %
#242
1#
b11000000000000000000000000011110 '
#243
0#
#244
1#
0&
b00000000000000000000000000011110 '
#245
0#
#246
1#
b01000000000000000000000000011110 '
#247
0#
#248
1#
1&
b10000000000000000000000000011110 '
#249
0#
#250
1#
b11000000000000000000000000011110 '
#251
0#
#252
1#
0&
b00000000000000000000000000011110 '
#253
0#
#254
1#
b01000000000000000000000000011110 '
#255
0#
#256
1#
1&
b10000000000000000000000000011110 '
#257
0#
#258
1#
b11000000000000000000000000011110 '
#259
0#
#260
1#
0&
b00000000000000000000000000011110 '
#261
0#
#262
1#
b01000000000000000000000000011110 '
#263
0#
#264
1#
1&
b10000000000000000000000000011110 '
#265
0#
#266
1#
b11000000000000000000000000011110 '
#267
0#
#268
1#
0&
b00000000000000000000000000011110 '
#269
0#
#270
1#
b01000000000000000000000000011110 '
#271
0#
#272
1#
1&
b10000000000000000000000000011110 '
