src/divider.v
module divider #(
    parameter DIV_VALUE = 10  // The divide ratio (N)
)(
    input  wire clk_in,   // Fast clock from DCO
    input  wire rst_n,    // Active low reset
    output reg  clk_out   // Slow clock to PFD
);

    // Counter width: Log2 of DIV_VALUE is enough, but 32 bits is safe for generic use
    reg [31:0] counter;

    always @(posedge clk_in or negedge rst_n) begin
        if (!rst_n) begin
            counter <= 0;
            clk_out <= 0;
        end else begin
            // Simple logic: Toggle clock every N/2 cycles to get 50% duty cycle
            // Note: This logic works best for EVEN divide ratios.
            // For N=10, we toggle every 5 ticks.
            if (counter >= (DIV_VALUE/2 - 1)) begin
                clk_out <= ~clk_out;
                counter <= 0;
            end else begin
                counter <= counter + 1;
            end
        end
    end

endmodule

test/tb_divider.v
`timescale 1ns / 1ps
module tb_divider;
    reg clk;
    reg rst_n;
    wire slow_clk;

    // Divide by 4
    divider #(.DIV_VALUE(4)) u_div (
        .clk_in(clk),
        .rst_n(rst_n),
        .clk_out(slow_clk)
    );

    always #5 clk = ~clk; // 100MHz input

    initial begin
        $dumpfile("build/tb_divider.vcd");
        $dumpvars(0, tb_divider);
        clk = 0; rst_n = 0;
        #20 rst_n = 1;
        #500 $finish;
    end
endmodule

build/tb_divider.vcd
$date
	Sat Dec 13 16:10:45 2025
$end
$version
	Icarus Verilog
$end
$timescale
	1ps
$end
$scope module tb_divider $end
$var wire 1 ! slow_clk $end
$var reg 1 " clk $end
$var reg 1 # rst_n $end
$scope module u_div $end
$var wire 1 " clk_in $end
$var wire 1 # rst_n $end
$var parameter 32 $ DIV_VALUE $end
$var reg 1 ! clk_out $end
$var reg 32 % counter [31:0] $end
$upscope $end
$upscope $end
$enddefinitions $end
$comment Show the parameter values. $end
$dumpall
b100 $
$end
#0
$dumpvars
b0 %
0#
0"
0!
$end
#5000
1"
#10000
0"
#15000
1"
#20000
0"
1#
#25000
b1 %
1"
#30000
0"
#35000
b0 %
1!
1"
#40000
0"
#45000
b1 %
1"
#50000
0"
#55000
b0 %
0!
1"
#60000
0"
#65000
b1 %
1"
#70000
0"
#75000
b0 %
1!
1"
#80000
0"
#85000
b1 %
1"
#90000
0"
#95000
b0 %
0!
1"
#100000
0"
#105000
b1 %
1"
#110000
0"
#115000
b0 %
1!
1"
#120000
0"
#125000
b1 %
1"
#130000
0"
#135000
b0 %
0!
1"
#140000
0"
#145000
b1 %
1"
#150000
0"
#155000
b0 %
1!
1"
#160000
0"
#165000
b1 %
1"
#170000
0"
#175000
b0 %
0!
1"
#180000
0"
#185000
b1 %
1"
#190000
0"
#195000
b0 %
1!
1"
#200000
0"
#205000
b1 %
1"
#210000
0"
#215000
b0 %
0!
1"
#220000
0"
#225000
b1 %
1"
#230000
0"
#235000
b0 %
1!
1"
#240000
0"
#245000
b1 %
1"
#250000
0"
#255000
b0 %
0!
1"
#260000
0"
#265000
b1 %
1"
#270000
0"
#275000
b0 %
1!
1"
#280000
0"
#285000
b1 %
1"
#290000
0"
#295000
b0 %
0!
1"
#300000
0"
#305000
b1 %
1"
#310000
0"
#315000
b0 %
1!
1"
#320000
0"
#325000
b1 %
1"
#330000
0"
#335000
b0 %
0!
1"
#340000
0"
#345000
b1 %
1"
#350000
0"
#355000
b0 %
1!
1"
#360000
0"
#365000
b1 %
1"
#370000
0"
#375000
b0 %
0!
1"
#380000
0"
#385000
b1 %
1"
#390000
0"
#395000
b0 %
1!
1"
#400000
0"
#405000
b1 %
1"
#410000
0"
#415000
b0 %
0!
1"
#420000
0"
#425000
b1 %
1"
#430000
0"
#435000
b0 %
1!
1"
#440000
0"
#445000
b1 %
1"
#450000
0"
#455000
b0 %
0!
1"
#460000
0"
#465000
b1 %
1"
#470000
0"
#475000
b0 %
1!
1"
#480000
0"
#485000
b1 %
1"
#490000
0"
#495000
b0 %
0!
1"
#500000
0"
#505000
b1 %
1"
#510000
0"
#515000
b0 %
1!
1"
