src/loop_filter.v
module loop_filter #(
    parameter INITIAL_FREQ = 32'd42949673, // Start at ~1 MHz (for 100MHz system)
    parameter K_P = 1000,                  // Proportional Gain
    parameter K_I = 10                     // Integral Gain
)(
    input  wire        clk,        // System Clock (100 MHz)
    input  wire        rst_n,      // Reset
    input  wire        up,         // From PFD
    input  wire        down,       // From PFD
    output reg [31:0]  tuning_word // To DCO
);

    // 1. Convert PFD pulses to a signed error (+1, -1, or 0)
    // We use a signed 2-bit wire: 01 (+1), 11 (-1), 00 (0)
    wire signed [1:0] error_val;
    assign error_val = (up && !down) ? 2'sd1 : 
                       (!up && down) ? -2'sd1 : 2'sd0;

    // 2. Integral Path (Accumulator)
    reg signed [31:0] integrator;
    
    always @(posedge clk or negedge rst_n) begin
        if (!rst_n) begin
            integrator <= 0;
            tuning_word <= INITIAL_FREQ;
        end else begin
            // Update Integrator (accumulate error * Ki)
            // We use simple addition since error is just +1/-1
            if (error_val == 1) 
                integrator <= integrator + K_I;
            else if (error_val == -1) 
                integrator <= integrator - K_I;
            
            // Calculate Output: Base + (Error * Kp) + Integrator
            // Note: In real silicon, you must clamp/saturate this to avoid overflow!
            tuning_word <= INITIAL_FREQ + (error_val * K_P) + integrator;
        end
    end

endmodule

test/tb_loop_filter.v
`timescale 1ns / 1ps

module tb_loop_filter;

    reg clk;
    reg rst_n;
    reg up;
    reg down;
    wire [31:0] tuning_word;

    // Instantiate Loop Filter
    // Initial Freq = 1000, Kp = 10, Ki = 1
    loop_filter #(
        .INITIAL_FREQ(32'd1000), 
        .K_P(10), 
        .K_I(1)
    ) u_filter (
        .clk(clk),
        .rst_n(rst_n),
        .up(up),
        .down(down),
        .tuning_word(tuning_word)
    );

    // 100 MHz System Clock
    always #5 clk = ~clk;

    initial begin
        $dumpfile("build/tb_loop_filter.vcd");
        $dumpvars(0, tb_loop_filter);

        // Init
        clk = 0; rst_n = 0;
        up = 0; down = 0;

        // Release Reset
        #20 rst_n = 1;
        #20;

        // -------------------------------------------------
        // Test 1: "Too Slow" -> Force UP pulses
        // -------------------------------------------------
        $display("Time: %0t | Initial Tuning Word: %d", $time, tuning_word);
        
        up = 1; // Simulate PFD holding "UP" high
        #100;   // Hold for 10 clock cycles
        up = 0;
        
        $display("Time: %0t | After UP pulses: %d (Should be Higher)", $time, tuning_word);
        #50; // Wait to see it settle (Proportional part will vanish, Integral stays)

        // -------------------------------------------------
        // Test 2: "Too Fast" -> Force DOWN pulses
        // -------------------------------------------------
        down = 1; // Simulate PFD holding "DOWN" high
        #200;     // Hold for 20 clock cycles (longer than UP)
        down = 0;

        $display("Time: %0t | After DOWN pulses: %d (Should be Lower)", $time, tuning_word);
        #50;

        $finish;
    end

endmodule

build/tb_loop_filter.vcd
$date
	Sat Dec 13 16:28:17 2025
$end
$version
	Icarus Verilog
$end
$timescale
	1ps
$end
$scope module tb_loop_filter $end
$var wire 32 ! tuning_word [31:0] $end
$var reg 1 " clk $end
$var reg 1 # down $end
$var reg 1 $ rst_n $end
$var reg 1 % up $end
$scope module u_filter $end
$var wire 1 " clk $end
$var wire 1 # down $end
$var wire 1 $ rst_n $end
$var wire 1 % up $end
$var wire 2 & error_val [1:0] $end
$var parameter 32 ' INITIAL_FREQ $end
$var parameter 32 ( K_I $end
$var parameter 32 ) K_P $end
$var reg 32 * integrator [31:0] $end
$var reg 32 + tuning_word [31:0] $end
$upscope $end
$upscope $end
$enddefinitions $end
$comment Show the parameter values. $end
$dumpall
b1010 )
b1 (
b1111101000 '
$end
#0
$dumpvars
b1111101000 +
b0 *
b0 &
0%
0$
0#
0"
b1111101000 !
$end
#5000
1"
#10000
0"
#15000
1"
#20000
0"
1$
#25000
1"
#30000
0"
#35000
1"
#40000
b1 &
0"
1%
#45000
b1111110010 !
b1111110010 +
b1 *
1"
#50000
0"
#55000
b1111110011 !
b1111110011 +
b10 *
1"
#60000
0"
#65000
b1111110100 !
b1111110100 +
b11 *
1"
#70000
0"
#75000
b1111110101 !
b1111110101 +
b100 *
1"
#80000
0"
#85000
b1111110110 !
b1111110110 +
b101 *
1"
#90000
0"
#95000
b1111110111 !
b1111110111 +
b110 *
1"
#100000
0"
#105000
b1111111000 !
b1111111000 +
b111 *
1"
#110000
0"
#115000
b1111111001 !
b1111111001 +
b1000 *
1"
#120000
0"
#125000
b1111111010 !
b1111111010 +
b1001 *
1"
#130000
0"
#135000
b1111111011 !
b1111111011 +
b1010 *
1"
#140000
b0 &
0"
0%
#145000
b1111110010 !
b1111110010 +
1"
#150000
0"
#155000
1"
#160000
0"
#165000
1"
#170000
0"
#175000
1"
#180000
0"
#185000
1"
#190000
b11 &
0"
1#
#195000
b10000010000 !
b10000010000 +
b1001 *
1"
#200000
0"
#205000
b10000001111 !
b10000001111 +
b1000 *
1"
#210000
0"
#215000
b10000001110 !
b10000001110 +
b111 *
1"
#220000
0"
#225000
b10000001101 !
b10000001101 +
b110 *
1"
#230000
0"
#235000
b10000001100 !
b10000001100 +
b101 *
1"
#240000
0"
#245000
b10000001011 !
b10000001011 +
b100 *
1"
#250000
0"
#255000
b10000001010 !
b10000001010 +
b11 *
1"
#260000
0"
#265000
b10000001001 !
b10000001001 +
b10 *
1"
#270000
0"
#275000
b10000001000 !
b10000001000 +
b1 *
1"
#280000
0"
#285000
b10000000111 !
b10000000111 +
b0 *
1"
#290000
0"
#295000
b10000000110 !
b10000000110 +
b11111111111111111111111111111111 *
1"
#300000
0"
#305000
b10000000101 !
b10000000101 +
b11111111111111111111111111111110 *
1"
#310000
0"
#315000
b10000000100 !
b10000000100 +
b11111111111111111111111111111101 *
1"
#320000
0"
#325000
b10000000011 !
b10000000011 +
b11111111111111111111111111111100 *
1"
#330000
0"
#335000
b10000000010 !
b10000000010 +
b11111111111111111111111111111011 *
1"
#340000
0"
#345000
b10000000001 !
b10000000001 +
b11111111111111111111111111111010 *
1"
#350000
0"
#355000
b10000000000 !
b10000000000 +
b11111111111111111111111111111001 *
1"
#360000
0"
#365000
b1111111111 !
b1111111111 +
b11111111111111111111111111111000 *
1"
#370000
0"
#375000
b1111111110 !
b1111111110 +
b11111111111111111111111111110111 *
1"
#380000
0"
#385000
b1111111101 !
b1111111101 +
b11111111111111111111111111110110 *
1"
#390000
b0 &
0"
0#
#395000
b1111011110 !
b1111011110 +
1"
