src/pfd.v
module pfd (
    input  wire ref_clk,    // The Reference Clock
    input  wire fb_clk,     // The Feedback Clock (from DCO/Divider)
    input  wire rst_n,      // Global System Reset
    output reg  up,         // "Speed Up" pulse
    output reg  down        // "Slow Down" pulse
);

    // Internal wire for the reset condition
    wire reset_pfd;

    // The PFD Reset happens if BOTH outputs are high OR if global reset is low
    // Note: We invert rst_n because the DFFs usually expect active high clear in this specific structure
    assign reset_pfd = (up & down) | (!rst_n);

    // D-Flip-Flop for Reference Path
    // When ref_clk rises, 'up' goes High.
    // It stays High until 'reset_pfd' clears it.
    always @(posedge ref_clk or posedge reset_pfd) begin
        if (reset_pfd) begin
            up <= 1'b0;
        end else begin
            up <= 1'b1;
        end
    end

    // D-Flip-Flop for Feedback Path
    // When fb_clk rises, 'down' goes High.
    // It stays High until 'reset_pfd' clears it.
    always @(posedge fb_clk or posedge reset_pfd) begin
        if (reset_pfd) begin
            down <= 1'b0;
        end else begin
            down <= 1'b1;
        end
    end

endmodule

test/tb_pfd.v

module tb_pfd;

    reg ref_clk;
    reg fb_clk;
    reg rst_n;
    wire up;
    wire down;

    pfd u_pfd (
        .ref_clk(ref_clk),
        .fb_clk(fb_clk),
        .rst_n(rst_n),
        .up(up),
        .down(down)
    );

    // Generate VCD
    initial begin
        $dumpfile("build/tb_pfd.vcd");
        $dumpvars(0, tb_pfd);
    end

    // 1. Reference Clock: 100 MHz (10ns period)
    always #5 ref_clk = ~ref_clk;

    // 2. Feedback Clock: 90 MHz (11.11ns period) -> SLOWER
    // Since FB is slower, we expect 'UP' pulses to appear.
    always #5.55 fb_clk = ~fb_clk;

    initial begin
        // Init
        ref_clk = 0; 
        fb_clk = 0;
        rst_n = 0;
        
        #50 rst_n = 1;

        // Run for enough time to see the phase drift
        #2000;
        
        $finish;
    end

endmodule

build/tb_pfd.vcd
$date
	Sat Dec 13 15:40:29 2025
$end
$version
	Icarus Verilog
$end
$timescale
	1s
$end
$scope module tb_pfd $end
$var wire 1 ! up $end
$var wire 1 " down $end
$var reg 1 # fb_clk $end
$var reg 1 $ ref_clk $end
$var reg 1 % rst_n $end
$scope module u_pfd $end
$var wire 1 # fb_clk $end
$var wire 1 $ ref_clk $end
$var wire 1 & reset_pfd $end
$var wire 1 % rst_n $end
$var reg 1 " down $end
$var reg 1 ! up $end
$upscope $end
$upscope $end
$enddefinitions $end
$comment Show the parameter values. $end
$dumpall
$end
#0
$dumpvars
1&
0%
0$
0#
0"
0!
$end
#5
1$
#6
1#
#10
0$
#12
0#
#15
1$
#18
1#
#20
0$
#24
0#
#25
1$
#30
0$
1#
#35
1$
#36
0#
#40
0$
#42
1#
#45
1$
#48
0#
#50
0&
0$
1%
#54
1"
1#
#55
0"
0&
0!
1$
#60
0$
0#
#65
1!
1$
#66
0!
0&
0"
1#
#70
0$
#72
0#
#75
1!
1$
#78
0!
0&
0"
1#
#80
0$
#84
0#
#85
1!
1$
#90
0!
0&
0"
0$
1#
#95
1!
1$
#96
0#
#100
0$
#102
0!
0&
0"
1#
#105
1!
1$
#108
0#
#110
0$
#114
0!
0&
0"
1#
#115
1!
1$
#120
0$
0#
#125
1$
#126
0!
0&
0"
1#
#130
0$
#132
0#
#135
1!
1$
#138
0!
0&
0"
1#
#140
0$
#144
0#
#145
1!
1$
#150
0!
0&
0"
0$
1#
#155
1!
1$
#156
0#
#160
0$
#162
0!
0&
0"
1#
#165
1!
1$
#168
0#
#170
0$
#174
0!
0&
0"
1#
#175
1!
1$
#180
0$
0#
#185
1$
#186
0!
0&
0"
1#
#190
0$
#192
0#
#195
1!
1$
#198
0!
0&
0"
1#
#200
0$
#204
0#
#205
1!
1$
#210
0!
0&
0"
0$
1#
#215
1!
1$
#216
0#
#220
0$
#222
0!
0&
0"
1#
#225
1!
1$
#228
0#
#230
0$
#234
0!
0&
0"
1#
#235
1!
1$
#240
0$
0#
#245
1$
#246
0!
0&
0"
1#
#250
0$
#252
0#
#255
1!
1$
#258
0!
0&
0"
1#
#260
0$
#264
0#
#265
1!
1$
#270
0!
0&
0"
0$
1#
#275
1!
1$
#276
0#
#280
0$
#282
0!
0&
0"
1#
#285
1!
1$
#288
0#
#290
0$
#294
0!
0&
0"
1#
#295
1!
1$
#300
0$
0#
#305
1$
#306
0!
0&
0"
1#
#310
0$
#312
0#
#315
1!
1$
#318
0!
0&
0"
1#
#320
0$
#324
0#
#325
1!
1$
#330
0!
0&
0"
0$
1#
#335
1!
1$
#336
0#
#340
0$
#342
0!
0&
0"
1#
#345
1!
1$
#348
0#
#350
0$
#354
0!
0&
0"
1#
#355
1!
1$
#360
0$
0#
#365
1$
#366
0!
0&
0"
1#
#370
0$
#372
0#
#375
1!
1$
#378
0!
0&
0"
1#
#380
0$
#384
0#
#385
1!
1$
#390
0!
0&
0"
0$
1#
#395
1!
1$
#396
0#
#400
0$
#402
0!
0&
0"
1#
#405
1!
1$
#408
0#
#410
0$
#414
0!
0&
0"
1#
#415
1!
1$
#420
0$
0#
#425
1$
#426
0!
0&
0"
1#
#430
0$
#432
0#
#435
1!
1$
#438
0!
0&
0"
1#
#440
0$
#444
0#
#445
1!
1$
#450
0!
0&
0"
0$
1#
#455
1!
1$
#456
0#
#460
0$
#462
0!
0&
0"
1#
#465
1!
1$
#468
0#
#470
0$
#474
0!
0&
0"
1#
#475
1!
1$
#480
0$
0#
#485
1$
#486
0!
0&
0"
1#
#490
0$
#492
0#
#495
1!
1$
#498
0!
0&
0"
1#
#500
0$
#504
0#
#505
1!
1$
#510
0!
0&
0"
0$
1#
#515
1!
1$
#516
0#
#520
0$
#522
0!
0&
0"
1#
#525
1!
1$
#528
0#
#530
0$
#534
0!
0&
0"
1#
#535
1!
1$
#540
0$
0#
#545
1$
#546
0!
0&
0"
1#
#550
0$
#552
0#
#555
1!
1$
#558
0!
0&
0"
1#
#560
0$
#564
0#
#565
1!
1$
#570
0!
0&
0"
0$
1#
#575
1!
1$
#576
0#
#580
0$
#582
0!
0&
0"
1#
#585
1!
1$
#588
0#
#590
0$
#594
0!
0&
0"
1#
#595
1!
1$
#600
0$
0#
#605
1$
#606
0!
0&
0"
1#
#610
0$
#612
0#
#615
1!
1$
#618
0!
0&
0"
1#
#620
0$
#624
0#
#625
1!
1$
#630
0!
0&
0"
0$
1#
#635
1!
1$
#636
0#
#640
0$
#642
0!
0&
0"
1#
#645
1!
1$
#648
0#
#650
0$
#654
0!
0&
0"
1#
#655
1!
1$
#660
0$
0#
#665
1$
#666
0!
0&
0"
1#
#670
0$
#672
0#
#675
1!
1$
#678
0!
0&
0"
1#
#680
0$
#684
0#
#685
1!
1$
#690
0!
0&
0"
0$
1#
#695
1!
1$
#696
0#
#700
0$
#702
0!
0&
0"
1#
#705
1!
1$
#708
0#
#710
0$
#714
0!
0&
0"
1#
#715
1!
1$
#720
0$
0#
#725
1$
#726
0!
0&
0"
1#
#730
0$
#732
0#
#735
1!
1$
#738
0!
0&
0"
1#
#740
0$
#744
0#
#745
1!
1$
#750
0!
0&
0"
0$
1#
#755
1!
1$
#756
0#
#760
0$
#762
0!
0&
0"
1#
#765
1!
1$
#768
0#
#770
0$
#774
0!
0&
0"
1#
#775
1!
1$
#780
0$
0#
#785
1$
#786
0!
0&
0"
1#
#790
0$
#792
0#
#795
1!
1$
#798
0!
0&
0"
1#
#800
0$
#804
0#
#805
1!
1$
#810
0!
0&
0"
0$
1#
#815
1!
1$
#816
0#
#820
0$
#822
0!
0&
0"
1#
#825
1!
1$
#828
0#
#830
0$
#834
0!
0&
0"
1#
#835
1!
1$
#840
0$
0#
#845
1$
#846
0!
0&
0"
1#
#850
0$
#852
0#
#855
1!
1$
#858
0!
0&
0"
1#
#860
0$
#864
0#
#865
1!
1$
#870
0!
0&
0"
0$
1#
#875
1!
1$
#876
0#
#880
0$
#882
0!
0&
0"
1#
#885
1!
1$
#888
0#
#890
0$
#894
0!
0&
0"
1#
#895
1!
1$
#900
0$
0#
#905
1$
#906
0!
0&
0"
1#
#910
0$
#912
0#
#915
1!
1$
#918
0!
0&
0"
1#
#920
0$
#924
0#
#925
1!
1$
#930
0!
0&
0"
0$
1#
#935
1!
1$
#936
0#
#940
0$
#942
0!
0&
0"
1#
#945
1!
1$
#948
0#
#950
0$
#954
0!
0&
0"
1#
#955
1!
1$
#960
0$
0#
#965
1$
#966
0!
0&
0"
1#
#970
0$
#972
0#
#975
1!
1$
#978
0!
0&
0"
1#
#980
0$
#984
0#
#985
1!
1$
#990
0!
0&
0"
0$
1#
#995
1!
1$
#996
0#
#1000
0$
#1002
0!
0&
0"
1#
#1005
1!
1$
#1008
0#
#1010
0$
#1014
0!
0&
0"
1#
#1015
1!
1$
#1020
0$
0#
#1025
1$
#1026
0!
0&
0"
1#
#1030
0$
#1032
0#
#1035
1!
1$
#1038
0!
0&
0"
1#
#1040
0$
#1044
0#
#1045
1!
1$
#1050
0!
0&
0"
0$
1#
#1055
1!
1$
#1056
0#
#1060
0$
#1062
0!
0&
0"
1#
#1065
1!
1$
#1068
0#
#1070
0$
#1074
0!
0&
0"
1#
#1075
1!
1$
#1080
0$
0#
#1085
1$
#1086
0!
0&
0"
1#
#1090
0$
#1092
0#
#1095
1!
1$
#1098
0!
0&
0"
1#
#1100
0$
#1104
0#
#1105
1!
1$
#1110
0!
0&
0"
0$
1#
#1115
1!
1$
#1116
0#
#1120
0$
#1122
0!
0&
0"
1#
#1125
1!
1$
#1128
0#
#1130
0$
#1134
0!
0&
0"
1#
#1135
1!
1$
#1140
0$
0#
#1145
1$
#1146
0!
0&
0"
1#
#1150
0$
#1152
0#
#1155
1!
1$
#1158
0!
0&
0"
1#
#1160
0$
#1164
0#
#1165
1!
1$
#1170
0!
0&
0"
0$
1#
#1175
1!
1$
#1176
0#
#1180
0$
#1182
0!
0&
0"
1#
#1185
1!
1$
#1188
0#
#1190
0$
#1194
0!
0&
0"
1#
#1195
1!
1$
#1200
0$
0#
#1205
1$
#1206
0!
0&
0"
1#
#1210
0$
#1212
0#
#1215
1!
1$
#1218
0!
0&
0"
1#
#1220
0$
#1224
0#
#1225
1!
1$
#1230
0!
0&
0"
0$
1#
#1235
1!
1$
#1236
0#
#1240
0$
#1242
0!
0&
0"
1#
#1245
1!
1$
#1248
0#
#1250
0$
#1254
0!
0&
0"
1#
#1255
1!
1$
#1260
0$
0#
#1265
1$
#1266
0!
0&
0"
1#
#1270
0$
#1272
0#
#1275
1!
1$
#1278
0!
0&
0"
1#
#1280
0$
#1284
0#
#1285
1!
1$
#1290
0!
0&
0"
0$
1#
#1295
1!
1$
#1296
0#
#1300
0$
#1302
0!
0&
0"
1#
#1305
1!
1$
#1308
0#
#1310
0$
#1314
0!
0&
0"
1#
#1315
1!
1$
#1320
0$
0#
#1325
1$
#1326
0!
0&
0"
1#
#1330
0$
#1332
0#
#1335
1!
1$
#1338
0!
0&
0"
1#
#1340
0$
#1344
0#
#1345
1!
1$
#1350
0!
0&
0"
0$
1#
#1355
1!
1$
#1356
0#
#1360
0$
#1362
0!
0&
0"
1#
#1365
1!
1$
#1368
0#
#1370
0$
#1374
0!
0&
0"
1#
#1375
1!
1$
#1380
0$
0#
#1385
1$
#1386
0!
0&
0"
1#
#1390
0$
#1392
0#
#1395
1!
1$
#1398
0!
0&
0"
1#
#1400
0$
#1404
0#
#1405
1!
1$
#1410
0!
0&
0"
0$
1#
#1415
1!
1$
#1416
0#
#1420
0$
#1422
0!
0&
0"
1#
#1425
1!
1$
#1428
0#
#1430
0$
#1434
0!
0&
0"
1#
#1435
1!
1$
#1440
0$
0#
#1445
1$
#1446
0!
0&
0"
1#
#1450
0$
#1452
0#
#1455
1!
1$
#1458
0!
0&
0"
1#
#1460
0$
#1464
0#
#1465
1!
1$
#1470
0!
0&
0"
0$
1#
#1475
1!
1$
#1476
0#
#1480
0$
#1482
0!
0&
0"
1#
#1485
1!
1$
#1488
0#
#1490
0$
#1494
0!
0&
0"
1#
#1495
1!
1$
#1500
0$
0#
#1505
1$
#1506
0!
0&
0"
1#
#1510
0$
#1512
0#
#1515
1!
1$
#1518
0!
0&
0"
1#
#1520
0$
#1524
0#
#1525
1!
1$
#1530
0!
0&
0"
0$
1#
#1535
1!
1$
#1536
0#
#1540
0$
#1542
0!
0&
0"
1#
#1545
1!
1$
#1548
0#
#1550
0$
#1554
0!
0&
0"
1#
#1555
1!
1$
#1560
0$
0#
#1565
1$
#1566
0!
0&
0"
1#
#1570
0$
#1572
0#
#1575
1!
1$
#1578
0!
0&
0"
1#
#1580
0$
#1584
0#
#1585
1!
1$
#1590
0!
0&
0"
0$
1#
#1595
1!
1$
#1596
0#
#1600
0$
#1602
0!
0&
0"
1#
#1605
1!
1$
#1608
0#
#1610
0$
#1614
0!
0&
0"
1#
#1615
1!
1$
#1620
0$
0#
#1625
1$
#1626
0!
0&
0"
1#
#1630
0$
#1632
0#
#1635
1!
1$
#1638
0!
0&
0"
1#
#1640
0$
#1644
0#
#1645
1!
1$
#1650
0!
0&
0"
0$
1#
#1655
1!
1$
#1656
0#
#1660
0$
#1662
0!
0&
0"
1#
#1665
1!
1$
#1668
0#
#1670
0$
#1674
0!
0&
0"
1#
#1675
1!
1$
#1680
0$
0#
#1685
1$
#1686
0!
0&
0"
1#
#1690
0$
#1692
0#
#1695
1!
1$
#1698
0!
0&
0"
1#
#1700
0$
#1704
0#
#1705
1!
1$
#1710
0!
0&
0"
0$
1#
#1715
1!
1$
#1716
0#
#1720
0$
#1722
0!
0&
0"
1#
#1725
1!
1$
#1728
0#
#1730
0$
#1734
0!
0&
0"
1#
#1735
1!
1$
#1740
0$
0#
#1745
1$
#1746
0!
0&
0"
1#
#1750
0$
#1752
0#
#1755
1!
1$
#1758
0!
0&
0"
1#
#1760
0$
#1764
0#
#1765
1!
1$
#1770
0!
0&
0"
0$
1#
#1775
1!
1$
#1776
0#
#1780
0$
#1782
0!
0&
0"
1#
#1785
1!
1$
#1788
0#
#1790
0$
#1794
0!
0&
0"
1#
#1795
1!
1$
#1800
0$
0#
#1805
1$
#1806
0!
0&
0"
1#
#1810
0$
#1812
0#
#1815
1!
1$
#1818
0!
0&
0"
1#
#1820
0$
#1824
0#
#1825
1!
1$
#1830
0!
0&
0"
0$
1#
#1835
1!
1$
#1836
0#
#1840
0$
#1842
0!
0&
0"
1#
#1845
1!
1$
#1848
0#
#1850
0$
#1854
0!
0&
0"
1#
#1855
1!
1$
#1860
0$
0#
#1865
1$
#1866
0!
0&
0"
1#
#1870
0$
#1872
0#
#1875
1!
1$
#1878
0!
0&
0"
1#
#1880
0$
#1884
0#
#1885
1!
1$
#1890
0!
0&
0"
0$
1#
#1895
1!
1$
#1896
0#
#1900
0$
#1902
0!
0&
0"
1#
#1905
1!
1$
#1908
0#
#1910
0$
#1914
0!
0&
0"
1#
#1915
1!
1$
#1920
0$
0#
#1925
1$
#1926
0!
0&
0"
1#
#1930
0$
#1932
0#
#1935
1!
1$
#1938
0!
0&
0"
1#
#1940
0$
#1944
0#
#1945
1!
1$
#1950
0!
0&
0"
0$
1#
#1955
1!
1$
#1956
0#
#1960
0$
#1962
0!
0&
0"
1#
#1965
1!
1$
#1968
0#
#1970
0$
#1974
0!
0&
0"
1#
#1975
1!
1$
#1980
0$
0#
#1985
1$
#1986
0!
0&
0"
1#
#1990
0$
#1992
0#
#1995
1!
1$
#1998
0!
0&
0"
1#
#2000
0$
#2004
0#
#2005
1!
1$
#2010
0!
0&
0"
0$
1#
#2015
1!
1$
#2016
0#
#2020
0$
#2022
0!
0&
0"
1#
#2025
1!
1$
#2028
0#
#2030
0$
#2034
0!
0&
0"
1#
#2035
1!
1$
#2040
0$
0#
#2045
1$
#2046
0!
0&
0"
1#
