src/dco_nco.v
module dco_nco #(
    parameter WIDTH = 32  // Accumulator width. Higher = finer frequency resolution
)(
    input  wire             sys_clk,      // System clock (e.g., 100MHz)
    input  wire             rst_n,        // Active low reset
    input  wire [WIDTH-1:0] tuning_word,  // Control input (sets frequency)
    output wire             dco_out       // Generated output clock
);

    // The Phase Accumulator
    reg [WIDTH-1:0] accumulator;

    always @(posedge sys_clk or negedge rst_n) begin
        if (!rst_n) begin
            accumulator <= {WIDTH{1'b0}};
        end else begin
            // Increment phase by the tuning word every cycle
            accumulator <= accumulator + tuning_word;
        end
    end

    // The MSB is the output clock (50% duty cycle on average, but with jitter)
    assign dco_out = accumulator[WIDTH-1];

endmodule

build/waveform_dco_func.vcd
$version Generated by VerilatedVcd $end
$timescale 1ps $end
 $scope module TOP $end
  $var wire 1 # sys_clk $end
  $var wire 1 $ rst_n $end
  $var wire 32 % tuning_word [31:0] $end
  $var wire 1 & dco_out $end
  $scope module dco_nco $end
   $var wire 32 ( WIDTH [31:0] $end
   $var wire 1 # sys_clk $end
   $var wire 1 $ rst_n $end
   $var wire 32 % tuning_word [31:0] $end
   $var wire 1 & dco_out $end
   $var wire 32 ' accumulator [31:0] $end
  $upscope $end
 $upscope $end
$enddefinitions $end


#0
1#
0$
b00000000000000000000000000000000 %
0&
b00000000000000000000000000000000 '
b00000000000000000000000000100000 (
#1
0#
#2
1#
#3
0#
#4
1#
#5
0#
#6
1#
#7
0#
#8
1#
#9
0#
#10
1#
#11
0#
#12
1#
#13
0#
#14
1#
#15
0#
#16
1#
#17
0#
#18
1#
#19
0#
#20
1#
1$
b00000010100011110101110000101000 %
b00000010100011110101110000101000 '
#21
0#
#22
1#
b00000101000111101011100001010000 '
#23
0#
#24
1#
b00000111101011100001010001111000 '
#25
0#
#26
1#
b00001010001111010111000010100000 '
#27
0#
#28
1#
b00001100110011001100110011001000 '
#29
0#
#30
1#
b00001111010111000010100011110000 '
#31
0#
#32
1#
b00010001111010111000010100011000 '
#33
0#
#34
1#
b00010100011110101110000101000000 '
#35
0#
#36
1#
b00010111000010100011110101101000 '
#37
0#
#38
1#
b00011001100110011001100110010000 '
#39
0#
#40
1#
b00011100001010001111010110111000 '
#41
0#
#42
1#
b00011110101110000101000111100000 '
#43
0#
#44
1#
b00100001010001111010111000001000 '
#45
0#
#46
1#
b00100011110101110000101000110000 '
#47
0#
#48
1#
b00100110011001100110011001011000 '
#49
0#
#50
1#
b00101000111101011100001010000000 '
#51
0#
#52
1#
b00101011100001010001111010101000 '
#53
0#
#54
1#
b00101110000101000111101011010000 '
#55
0#
#56
1#
b00110000101000111101011011111000 '
#57
0#
#58
1#
b00110011001100110011001100100000 '
#59
0#
#60
1#
b00110101110000101000111101001000 '
#61
0#
#62
1#
b00111000010100011110101101110000 '
#63
0#
#64
1#
b00111010111000010100011110011000 '
#65
0#
#66
1#
b00111101011100001010001111000000 '
#67
0#
#68
1#
b00111111111111111111111111101000 '
#69
0#
#70
1#
b01000010100011110101110000010000 '
#71
0#
#72
1#
b01000101000111101011100000111000 '
#73
0#
#74
1#
b01000111101011100001010001100000 '
#75
0#
#76
1#
b01001010001111010111000010001000 '
#77
0#
#78
1#
b01001100110011001100110010110000 '
#79
0#
#80
1#
b01001111010111000010100011011000 '
#81
0#
#82
1#
b01010001111010111000010100000000 '
#83
0#
#84
1#
b01010100011110101110000100101000 '
#85
0#
#86
1#
b01010111000010100011110101010000 '
#87
0#
#88
1#
b01011001100110011001100101111000 '
#89
0#
#90
1#
b01011100001010001111010110100000 '
#91
0#
#92
1#
b01011110101110000101000111001000 '
#93
0#
#94
1#
b01100001010001111010110111110000 '
#95
0#
#96
1#
b01100011110101110000101000011000 '
#97
0#
#98
1#
b01100110011001100110011001000000 '
#99
0#
#100
1#
b01101000111101011100001001101000 '
#101
0#
#102
1#
b01101011100001010001111010010000 '
#103
0#
#104
1#
b01101110000101000111101010111000 '
#105
0#
#106
1#
b01110000101000111101011011100000 '
#107
0#
#108
1#
b01110011001100110011001100001000 '
#109
0#
#110
1#
b01110101110000101000111100110000 '
#111
0#
#112
1#
b01111000010100011110101101011000 '
#113
0#
#114
1#
b01111010111000010100011110000000 '
#115
0#
#116
1#
b01111101011100001010001110101000 '
#117
0#
#118
1#
b01111111111111111111111111010000 '
#119
0#
#120
1#
1&
b10000010100011110101101111111000 '
#121
0#
#122
1#
b10000101000111101011100000100000 '
#123
0#
#124
1#
b10000111101011100001010001001000 '
#125
0#
#126
1#
b10001010001111010111000001110000 '
#127
0#
#128
1#
b10001100110011001100110010011000 '
#129
0#
#130
1#
b10001111010111000010100011000000 '
#131
0#
#132
1#
b10010001111010111000010011101000 '
#133
0#
#134
1#
b10010100011110101110000100010000 '
#135
0#
#136
1#
b10010111000010100011110100111000 '
#137
0#
#138
1#
b10011001100110011001100101100000 '
#139
0#
#140
1#
b10011100001010001111010110001000 '
#141
0#
#142
1#
b10011110101110000101000110110000 '
#143
0#
#144
1#
b10100001010001111010110111011000 '
#145
0#
#146
1#
b10100011110101110000101000000000 '
#147
0#
#148
1#
b10100110011001100110011000101000 '
#149
0#
#150
1#
b10101000111101011100001001010000 '
#151
0#
#152
1#
b10101011100001010001111001111000 '
#153
0#
#154
1#
b10101110000101000111101010100000 '
#155
0#
#156
1#
b10110000101000111101011011001000 '
#157
0#
#158
1#
b10110011001100110011001011110000 '
#159
0#
#160
1#
b10110101110000101000111100011000 '
#161
0#
#162
1#
b10111000010100011110101101000000 '
#163
0#
#164
1#
b10111010111000010100011101101000 '
#165
0#
#166
1#
b10111101011100001010001110010000 '
#167
0#
#168
1#
b10111111111111111111111110111000 '
#169
0#
#170
1#
b11000010100011110101101111100000 '
#171
0#
#172
1#
b11000101000111101011100000001000 '
#173
0#
#174
1#
b11000111101011100001010000110000 '
#175
0#
#176
1#
b11001010001111010111000001011000 '
#177
0#
#178
1#
b11001100110011001100110010000000 '
#179
0#
#180
1#
b11001111010111000010100010101000 '
#181
0#
#182
1#
b11010001111010111000010011010000 '
#183
0#
#184
1#
b11010100011110101110000011111000 '
#185
0#
#186
1#
b11010111000010100011110100100000 '
#187
0#
#188
1#
b11011001100110011001100101001000 '
#189
0#
#190
1#
b11011100001010001111010101110000 '
#191
0#
#192
1#
b11011110101110000101000110011000 '
#193
0#
#194
1#
b11100001010001111010110111000000 '
#195
0#
#196
1#
b11100011110101110000100111101000 '
#197
0#
#198
1#
b11100110011001100110011000010000 '
#199
0#
#200
1#
b11101000111101011100001000111000 '
#201
0#
#202
1#
b11101011100001010001111001100000 '
#203
0#
#204
1#
b11101110000101000111101010001000 '
#205
0#
#206
1#
b11110000101000111101011010110000 '
#207
0#
#208
1#
b11110011001100110011001011011000 '
#209
0#
#210
1#
b11110101110000101000111100000000 '
#211
0#
#212
1#
b11111000010100011110101100101000 '
#213
0#
#214
1#
b11111010111000010100011101010000 '
#215
0#
#216
1#
b11111101011100001010001101111000 '
#217
0#
#218
1#
b11111111111111111111111110100000 '
#219
0#
#220
1#
0&
b00000010100011110101101111001000 '
#221
0#
#222
1#
b00000101000111101011011111110000 '
#223
0#
#224
1#
b00000111101011100001010000011000 '
#225
0#
#226
1#
b00001010001111010111000001000000 '
#227
0#
#228
1#
b00001100110011001100110001101000 '
#229
0#
#230
1#
b00001111010111000010100010010000 '
#231
0#
#232
1#
b00010001111010111000010010111000 '
#233
0#
#234
1#
b00010100011110101110000011100000 '
#235
0#
#236
1#
b00010111000010100011110100001000 '
#237
0#
#238
1#
b00011001100110011001100100110000 '
#239
0#
#240
1#
b00011100001010001111010101011000 '
#241
0#
#242
1#
b00011110101110000101000110000000 '
#243
0#
#244
1#
b00100001010001111010110110101000 '
#245
0#
#246
1#
b00100011110101110000100111010000 '
#247
0#
#248
1#
b00100110011001100110010111111000 '
#249
0#
#250
1#
b00101000111101011100001000100000 '
#251
0#
#252
1#
b00101011100001010001111001001000 '
#253
0#
#254
1#
b00101110000101000111101001110000 '
#255
0#
#256
1#
b00110000101000111101011010011000 '
#257
0#
#258
1#
b00110011001100110011001011000000 '
#259
0#
#260
1#
b00110101110000101000111011101000 '
#261
0#
#262
1#
b00111000010100011110101100010000 '
#263
0#
#264
1#
b00111010111000010100011100111000 '
#265
0#
#266
1#
b00111101011100001010001101100000 '
#267
0#
#268
1#
b00111111111111111111111110001000 '
#269
0#
#270
1#
b01000010100011110101101110110000 '
#271
0#
#272
1#
b01000101000111101011011111011000 '
#273
0#
#274
1#
b01000111101011100001010000000000 '
#275
0#
#276
1#
b01001010001111010111000000101000 '
#277
0#
#278
1#
b01001100110011001100110001010000 '
#279
0#
#280
1#
b01001111010111000010100001111000 '
#281
0#
#282
1#
b01010001111010111000010010100000 '
#283
0#
#284
1#
b01010100011110101110000011001000 '
#285
0#
#286
1#
b01010111000010100011110011110000 '
#287
0#
#288
1#
b01011001100110011001100100011000 '
#289
0#
#290
1#
b01011100001010001111010101000000 '
#291
0#
#292
1#
b01011110101110000101000101101000 '
#293
0#
#294
1#
b01100001010001111010110110010000 '
#295
0#
#296
1#
b01100011110101110000100110111000 '
#297
0#
#298
1#
b01100110011001100110010111100000 '
#299
0#
#300
1#
b01101000111101011100001000001000 '
#301
0#
#302
1#
b01101011100001010001111000110000 '
#303
0#
#304
1#
b01101110000101000111101001011000 '
#305
0#
#306
1#
b01110000101000111101011010000000 '
#307
0#
#308
1#
b01110011001100110011001010101000 '
#309
0#
#310
1#
b01110101110000101000111011010000 '
#311
0#
#312
1#
b01111000010100011110101011111000 '
#313
0#
#314
1#
b01111010111000010100011100100000 '
#315
0#
#316
1#
b01111101011100001010001101001000 '
#317
0#
#318
1#
b01111111111111111111111101110000 '
#319
0#
#320
1#
1&
b10000010100011110101101110011000 '
#321
0#
#322
1#
b10000101000111101011011111000000 '
#323
0#
#324
1#
b10000111101011100001001111101000 '
#325
0#
#326
1#
b10001010001111010111000000010000 '
#327
0#
#328
1#
b10001100110011001100110000111000 '
#329
0#
#330
1#
b10001111010111000010100001100000 '
#331
0#
#332
1#
b10010001111010111000010010001000 '
#333
0#
#334
1#
b10010100011110101110000010110000 '
#335
0#
#336
1#
b10010111000010100011110011011000 '
#337
0#
#338
1#
b10011001100110011001100100000000 '
#339
0#
#340
1#
b10011100001010001111010100101000 '
#341
0#
#342
1#
b10011110101110000101000101010000 '
#343
0#
#344
1#
b10100001010001111010110101111000 '
#345
0#
#346
1#
b10100011110101110000100110100000 '
#347
0#
#348
1#
b10100110011001100110010111001000 '
#349
0#
#350
1#
b10101000111101011100000111110000 '
#351
0#
#352
1#
b10101011100001010001111000011000 '
#353
0#
#354
1#
b10101110000101000111101001000000 '
#355
0#
#356
1#
b10110000101000111101011001101000 '
#357
0#
#358
1#
b10110011001100110011001010010000 '
#359
0#
#360
1#
b10110101110000101000111010111000 '
#361
0#
#362
1#
b10111000010100011110101011100000 '
#363
0#
#364
1#
b10111010111000010100011100001000 '
#365
0#
#366
1#
b10111101011100001010001100110000 '
#367
0#
#368
1#
b10111111111111111111111101011000 '
#369
0#
#370
1#
b11000010100011110101101110000000 '
#371
0#
#372
1#
b11000101000111101011011110101000 '
#373
0#
#374
1#
b11000111101011100001001111010000 '
#375
0#
#376
1#
b11001010001111010110111111111000 '
#377
0#
#378
1#
b11001100110011001100110000100000 '
#379
0#
#380
1#
b11001111010111000010100001001000 '
#381
0#
#382
1#
b11010001111010111000010001110000 '
#383
0#
#384
1#
b11010100011110101110000010011000 '
#385
0#
#386
1#
b11010111000010100011110011000000 '
#387
0#
#388
1#
b11011001100110011001100011101000 '
#389
0#
#390
1#
b11011100001010001111010100010000 '
#391
0#
#392
1#
b11011110101110000101000100111000 '
#393
0#
#394
1#
b11100001010001111010110101100000 '
#395
0#
#396
1#
b11100011110101110000100110001000 '
#397
0#
#398
1#
b11100110011001100110010110110000 '
#399
0#
#400
1#
b11101000111101011100000111011000 '
#401
0#
#402
1#
b11101011100001010001111000000000 '
#403
0#
#404
1#
b11101110000101000111101000101000 '
#405
0#
#406
1#
b11110000101000111101011001010000 '
#407
0#
#408
1#
b11110011001100110011001001111000 '
#409
0#
#410
1#
b11110101110000101000111010100000 '
#411
0#
#412
1#
b11111000010100011110101011001000 '
#413
0#
#414
1#
b11111010111000010100011011110000 '
#415
0#
#416
1#
b11111101011100001010001100011000 '
#417
0#
#418
1#
b11111111111111111111111101000000 '
#419
0#
#420
1#
0&
b00000010100011110101101101101000 '
#421
0#
#422
1#
b00000101000111101011011110010000 '
#423
0#
#424
1#
b00000111101011100001001110111000 '
#425
0#
#426
1#
b00001010001111010110111111100000 '
#427
0#
#428
1#
b00001100110011001100110000001000 '
#429
0#
#430
1#
b00001111010111000010100000110000 '
#431
0#
#432
1#
b00010001111010111000010001011000 '
#433
0#
#434
1#
b00010100011110101110000010000000 '
#435
0#
#436
1#
b00010111000010100011110010101000 '
#437
0#
#438
1#
b00011001100110011001100011010000 '
#439
0#
#440
1#
b00011100001010001111010011111000 '
#441
0#
#442
1#
b00011110101110000101000100100000 '
#443
0#
#444
1#
b00100001010001111010110101001000 '
#445
0#
#446
1#
b00100011110101110000100101110000 '
#447
0#
#448
1#
b00100110011001100110010110011000 '
#449
0#
#450
1#
b00101000111101011100000111000000 '
#451
0#
#452
1#
b00101011100001010001110111101000 '
#453
0#
#454
1#
b00101110000101000111101000010000 '
#455
0#
#456
1#
b00110000101000111101011000111000 '
#457
0#
#458
1#
b00110011001100110011001001100000 '
#459
0#
#460
1#
b00110101110000101000111010001000 '
#461
0#
#462
1#
b00111000010100011110101010110000 '
#463
0#
#464
1#
b00111010111000010100011011011000 '
#465
0#
#466
1#
b00111101011100001010001100000000 '
#467
0#
#468
1#
b00111111111111111111111100101000 '
#469
0#
#470
1#
b01000010100011110101101101010000 '
#471
0#
#472
1#
b01000101000111101011011101111000 '
#473
0#
#474
1#
b01000111101011100001001110100000 '
#475
0#
#476
1#
b01001010001111010110111111001000 '
#477
0#
#478
1#
b01001100110011001100101111110000 '
#479
0#
#480
1#
b01001111010111000010100000011000 '
#481
0#
#482
1#
b01010001111010111000010001000000 '
#483
0#
#484
1#
b01010100011110101110000001101000 '
#485
0#
#486
1#
b01010111000010100011110010010000 '
#487
0#
#488
1#
b01011001100110011001100010111000 '
#489
0#
#490
1#
b01011100001010001111010011100000 '
#491
0#
#492
1#
b01011110101110000101000100001000 '
#493
0#
#494
1#
b01100001010001111010110100110000 '
#495
0#
#496
1#
b01100011110101110000100101011000 '
#497
0#
#498
1#
b01100110011001100110010110000000 '
#499
0#
#500
1#
b01101000111101011100000110101000 '
#501
0#
#502
1#
b01101011100001010001110111010000 '
#503
0#
#504
1#
b01101110000101000111100111111000 '
#505
0#
#506
1#
b01110000101000111101011000100000 '
#507
0#
#508
1#
b01110011001100110011001001001000 '
#509
0#
#510
1#
b01110101110000101000111001110000 '
#511
0#
#512
1#
b01111000010100011110101010011000 '
#513
0#
#514
1#
b01111010111000010100011011000000 '
#515
0#
#516
1#
b01111101011100001010001011101000 '
#517
0#
#518
1#
b01111111111111111111111100010000 '
#519
0#
#520
1#
1&
b10000010100011110101101100111000 '
#521
0#
#522
1#
b10000101000111101011011101100000 '
#523
0#
#524
1#
b10000111101011100001001110001000 '
#525
0#
#526
1#
b10001010001111010110111110110000 '
#527
0#
#528
1#
b10001100110011001100101111011000 '
#529
0#
#530
1#
b10001111010111000010100000000000 '
#531
0#
#532
1#
b10010001111010111000010000101000 '
#533
0#
#534
1#
b10010100011110101110000001010000 '
#535
0#
#536
1#
b10010111000010100011110001111000 '
#537
0#
#538
1#
b10011001100110011001100010100000 '
#539
0#
#540
1#
b10011100001010001111010011001000 '
#541
0#
#542
1#
b10011110101110000101000011110000 '
#543
0#
#544
1#
b10100001010001111010110100011000 '
#545
0#
#546
1#
b10100011110101110000100101000000 '
#547
0#
#548
1#
b10100110011001100110010101101000 '
#549
0#
#550
1#
b10101000111101011100000110010000 '
#551
0#
#552
1#
b10101011100001010001110110111000 '
#553
0#
#554
1#
b10101110000101000111100111100000 '
#555
0#
#556
1#
b10110000101000111101011000001000 '
#557
0#
#558
1#
b10110011001100110011001000110000 '
#559
0#
#560
1#
b10110101110000101000111001011000 '
#561
0#
#562
1#
b10111000010100011110101010000000 '
#563
0#
#564
1#
b10111010111000010100011010101000 '
#565
0#
#566
1#
b10111101011100001010001011010000 '
#567
0#
#568
1#
b10111111111111111111111011111000 '
#569
0#
#570
1#
b11000010100011110101101100100000 '
#571
0#
#572
1#
b11000101000111101011011101001000 '
#573
0#
#574
1#
b11000111101011100001001101110000 '
#575
0#
#576
1#
b11001010001111010110111110011000 '
#577
0#
#578
1#
b11001100110011001100101111000000 '
#579
0#
#580
1#
b11001111010111000010011111101000 '
#581
0#
#582
1#
b11010001111010111000010000010000 '
#583
0#
#584
1#
b11010100011110101110000000111000 '
#585
0#
#586
1#
b11010111000010100011110001100000 '
#587
0#
#588
1#
b11011001100110011001100010001000 '
#589
0#
#590
1#
b11011100001010001111010010110000 '
#591
0#
#592
1#
b11011110101110000101000011011000 '
#593
0#
#594
1#
b11100001010001111010110100000000 '
#595
0#
#596
1#
b11100011110101110000100100101000 '
#597
0#
#598
1#
b11100110011001100110010101010000 '
#599
0#
#600
1#
b11101000111101011100000101111000 '
#601
0#
#602
1#
b11101011100001010001110110100000 '
#603
0#
#604
1#
b11101110000101000111100111001000 '
#605
0#
#606
1#
b11110000101000111101010111110000 '
#607
0#
#608
1#
b11110011001100110011001000011000 '
#609
0#
#610
1#
b11110101110000101000111001000000 '
#611
0#
#612
1#
b11111000010100011110101001101000 '
#613
0#
#614
1#
b11111010111000010100011010010000 '
#615
0#
#616
1#
b11111101011100001010001010111000 '
#617
0#
#618
1#
b11111111111111111111111011100000 '
#619
0#
#620
1#
0&
b00000010100011110101101100001000 '
#621
0#
#622
1#
b00000101000111101011011100110000 '
#623
0#
#624
1#
b00000111101011100001001101011000 '
#625
0#
#626
1#
b00001010001111010110111110000000 '
#627
0#
#628
1#
b00001100110011001100101110101000 '
#629
0#
#630
1#
b00001111010111000010011111010000 '
#631
0#
#632
1#
b00010001111010111000001111111000 '
#633
0#
#634
1#
b00010100011110101110000000100000 '
#635
0#
#636
1#
b00010111000010100011110001001000 '
#637
0#
#638
1#
b00011001100110011001100001110000 '
#639
0#
#640
1#
b00011100001010001111010010011000 '
#641
0#
#642
1#
b00011110101110000101000011000000 '
#643
0#
#644
1#
b00100001010001111010110011101000 '
#645
0#
#646
1#
b00100011110101110000100100010000 '
#647
0#
#648
1#
b00100110011001100110010100111000 '
#649
0#
#650
1#
b00101000111101011100000101100000 '
#651
0#
#652
1#
b00101011100001010001110110001000 '
#653
0#
#654
1#
b00101110000101000111100110110000 '
#655
0#
#656
1#
b00110000101000111101010111011000 '
#657
0#
#658
1#
b00110011001100110011001000000000 '
#659
0#
#660
1#
b00110101110000101000111000101000 '
#661
0#
#662
1#
b00111000010100011110101001010000 '
#663
0#
#664
1#
b00111010111000010100011001111000 '
#665
0#
#666
1#
b00111101011100001010001010100000 '
#667
0#
#668
1#
b00111111111111111111111011001000 '
#669
0#
#670
1#
b01000010100011110101101011110000 '
#671
0#
#672
1#
b01000101000111101011011100011000 '
#673
0#
#674
1#
b01000111101011100001001101000000 '
#675
0#
#676
1#
b01001010001111010110111101101000 '
#677
0#
#678
1#
b01001100110011001100101110010000 '
#679
0#
#680
1#
b01001111010111000010011110111000 '
#681
0#
#682
1#
b01010001111010111000001111100000 '
#683
0#
#684
1#
b01010100011110101110000000001000 '
#685
0#
#686
1#
b01010111000010100011110000110000 '
#687
0#
#688
1#
b01011001100110011001100001011000 '
#689
0#
#690
1#
b01011100001010001111010010000000 '
#691
0#
#692
1#
b01011110101110000101000010101000 '
#693
0#
#694
1#
b01100001010001111010110011010000 '
#695
0#
#696
1#
b01100011110101110000100011111000 '
#697
0#
#698
1#
b01100110011001100110010100100000 '
#699
0#
#700
1#
b01101000111101011100000101001000 '
#701
0#
#702
1#
b01101011100001010001110101110000 '
#703
0#
#704
1#
b01101110000101000111100110011000 '
#705
0#
#706
1#
b01110000101000111101010111000000 '
#707
0#
#708
1#
b01110011001100110011000111101000 '
#709
0#
#710
1#
b01110101110000101000111000010000 '
#711
0#
#712
1#
b01111000010100011110101000111000 '
#713
0#
#714
1#
b01111010111000010100011001100000 '
#715
0#
#716
1#
b01111101011100001010001010001000 '
#717
0#
#718
1#
b01111111111111111111111010110000 '
#719
0#
#720
1#
1&
b10000010100011110101101011011000 '
#721
0#
#722
1#
b10000101000111101011011100000000 '
#723
0#
#724
1#
b10000111101011100001001100101000 '
#725
0#
#726
1#
b10001010001111010110111101010000 '
#727
0#
#728
1#
b10001100110011001100101101111000 '
#729
0#
#730
1#
b10001111010111000010011110100000 '
#731
0#
#732
1#
b10010001111010111000001111001000 '
#733
0#
#734
1#
b10010100011110101101111111110000 '
#735
0#
#736
1#
b10010111000010100011110000011000 '
#737
0#
#738
1#
b10011001100110011001100001000000 '
#739
0#
#740
1#
b10011100001010001111010001101000 '
#741
0#
#742
1#
b10011110101110000101000010010000 '
#743
0#
#744
1#
b10100001010001111010110010111000 '
#745
0#
#746
1#
b10100011110101110000100011100000 '
#747
0#
#748
1#
b10100110011001100110010100001000 '
#749
0#
#750
1#
b10101000111101011100000100110000 '
#751
0#
#752
1#
b10101011100001010001110101011000 '
#753
0#
#754
1#
b10101110000101000111100110000000 '
#755
0#
#756
1#
b10110000101000111101010110101000 '
#757
0#
#758
1#
b10110011001100110011000111010000 '
#759
0#
#760
1#
b10110101110000101000110111111000 '
#761
0#
#762
1#
b10111000010100011110101000100000 '
#763
0#
#764
1#
b10111010111000010100011001001000 '
#765
0#
#766
1#
b10111101011100001010001001110000 '
#767
0#
#768
1#
b10111111111111111111111010011000 '
#769
0#
#770
1#
b11000010100011110101101011000000 '
#771
0#
#772
1#
b11000101000111101011011011101000 '
#773
0#
#774
1#
b11000111101011100001001100010000 '
#775
0#
#776
1#
b11001010001111010110111100111000 '
#777
0#
#778
1#
b11001100110011001100101101100000 '
#779
0#
#780
1#
b11001111010111000010011110001000 '
#781
0#
#782
1#
b11010001111010111000001110110000 '
#783
0#
#784
1#
b11010100011110101101111111011000 '
#785
0#
#786
1#
b11010111000010100011110000000000 '
#787
0#
#788
1#
b11011001100110011001100000101000 '
#789
0#
#790
1#
b11011100001010001111010001010000 '
#791
0#
#792
1#
b11011110101110000101000001111000 '
#793
0#
#794
1#
b11100001010001111010110010100000 '
#795
0#
#796
1#
b11100011110101110000100011001000 '
#797
0#
#798
1#
b11100110011001100110010011110000 '
#799
0#
#800
1#
b11101000111101011100000100011000 '
#801
0#
#802
1#
b11101011100001010001110101000000 '
#803
0#
#804
1#
b11101110000101000111100101101000 '
#805
0#
#806
1#
b11110000101000111101010110010000 '
#807
0#
#808
1#
b11110011001100110011000110111000 '
#809
0#
#810
1#
b11110101110000101000110111100000 '
#811
0#
#812
1#
b11111000010100011110101000001000 '
#813
0#
#814
1#
b11111010111000010100011000110000 '
#815
0#
#816
1#
b11111101011100001010001001011000 '
#817
0#
#818
1#
b11111111111111111111111010000000 '
#819
0#
#820
1#
0&
b00000010100011110101101010101000 '
#821
0#
#822
1#
b00000101000111101011011011010000 '
#823
0#
#824
1#
b00000111101011100001001011111000 '
#825
0#
#826
1#
b00001010001111010110111100100000 '
#827
0#
#828
1#
b00001100110011001100101101001000 '
#829
0#
#830
1#
b00001111010111000010011101110000 '
#831
0#
#832
1#
b00010001111010111000001110011000 '
#833
0#
#834
1#
b00010100011110101101111111000000 '
#835
0#
#836
1#
b00010111000010100011101111101000 '
#837
0#
#838
1#
b00011001100110011001100000010000 '
#839
0#
#840
1#
b00011100001010001111010000111000 '
#841
0#
#842
1#
b00011110101110000101000001100000 '
#843
0#
#844
1#
b00100001010001111010110010001000 '
#845
0#
#846
1#
b00100011110101110000100010110000 '
#847
0#
#848
1#
b00100110011001100110010011011000 '
#849
0#
#850
1#
b00101000111101011100000100000000 '
#851
0#
#852
1#
b00101011100001010001110100101000 '
#853
0#
#854
1#
b00101110000101000111100101010000 '
#855
0#
#856
1#
b00110000101000111101010101111000 '
#857
0#
#858
1#
b00110011001100110011000110100000 '
#859
0#
#860
1#
b00110101110000101000110111001000 '
#861
0#
#862
1#
b00111000010100011110100111110000 '
#863
0#
#864
1#
b00111010111000010100011000011000 '
#865
0#
#866
1#
b00111101011100001010001001000000 '
#867
0#
#868
1#
b00111111111111111111111001101000 '
#869
0#
#870
1#
b01000010100011110101101010010000 '
#871
0#
#872
1#
b01000101000111101011011010111000 '
#873
0#
#874
1#
b01000111101011100001001011100000 '
#875
0#
#876
1#
b01001010001111010110111100001000 '
#877
0#
#878
1#
b01001100110011001100101100110000 '
#879
0#
#880
1#
b01001111010111000010011101011000 '
#881
0#
#882
1#
b01010001111010111000001110000000 '
#883
0#
#884
1#
b01010100011110101101111110101000 '
#885
0#
#886
1#
b01010111000010100011101111010000 '
#887
0#
#888
1#
b01011001100110011001011111111000 '
#889
0#
#890
1#
b01011100001010001111010000100000 '
#891
0#
#892
1#
b01011110101110000101000001001000 '
#893
0#
#894
1#
b01100001010001111010110001110000 '
#895
0#
#896
1#
b01100011110101110000100010011000 '
#897
0#
#898
1#
b01100110011001100110010011000000 '
#899
0#
#900
1#
b01101000111101011100000011101000 '
#901
0#
#902
1#
b01101011100001010001110100010000 '
#903
0#
#904
1#
b01101110000101000111100100111000 '
#905
0#
#906
1#
b01110000101000111101010101100000 '
#907
0#
#908
1#
b01110011001100110011000110001000 '
#909
0#
#910
1#
b01110101110000101000110110110000 '
#911
0#
#912
1#
b01111000010100011110100111011000 '
#913
0#
#914
1#
b01111010111000010100011000000000 '
#915
0#
#916
1#
b01111101011100001010001000101000 '
#917
0#
#918
1#
b01111111111111111111111001010000 '
#919
0#
#920
1#
1&
b10000010100011110101101001111000 '
#921
0#
#922
1#
b10000101000111101011011010100000 '
#923
0#
#924
1#
b10000111101011100001001011001000 '
#925
0#
#926
1#
b10001010001111010110111011110000 '
#927
0#
#928
1#
b10001100110011001100101100011000 '
#929
0#
#930
1#
b10001111010111000010011101000000 '
#931
0#
#932
1#
b10010001111010111000001101101000 '
#933
0#
#934
1#
b10010100011110101101111110010000 '
#935
0#
#936
1#
b10010111000010100011101110111000 '
#937
0#
#938
1#
b10011001100110011001011111100000 '
#939
0#
#940
1#
b10011100001010001111010000001000 '
#941
0#
#942
1#
b10011110101110000101000000110000 '
#943
0#
#944
1#
b10100001010001111010110001011000 '
#945
0#
#946
1#
b10100011110101110000100010000000 '
#947
0#
#948
1#
b10100110011001100110010010101000 '
#949
0#
#950
1#
b10101000111101011100000011010000 '
#951
0#
#952
1#
b10101011100001010001110011111000 '
#953
0#
#954
1#
b10101110000101000111100100100000 '
#955
0#
#956
1#
b10110000101000111101010101001000 '
#957
0#
#958
1#
b10110011001100110011000101110000 '
#959
0#
#960
1#
b10110101110000101000110110011000 '
#961
0#
#962
1#
b10111000010100011110100111000000 '
#963
0#
#964
1#
b10111010111000010100010111101000 '
#965
0#
#966
1#
b10111101011100001010001000010000 '
#967
0#
#968
1#
b10111111111111111111111000111000 '
#969
0#
#970
1#
b11000010100011110101101001100000 '
#971
0#
#972
1#
b11000101000111101011011010001000 '
#973
0#
#974
1#
b11000111101011100001001010110000 '
#975
0#
#976
1#
b11001010001111010110111011011000 '
#977
0#
#978
1#
b11001100110011001100101100000000 '
#979
0#
#980
1#
b11001111010111000010011100101000 '
#981
0#
#982
1#
b11010001111010111000001101010000 '
#983
0#
#984
1#
b11010100011110101101111101111000 '
#985
0#
#986
1#
b11010111000010100011101110100000 '
#987
0#
#988
1#
b11011001100110011001011111001000 '
#989
0#
#990
1#
b11011100001010001111001111110000 '
#991
0#
#992
1#
b11011110101110000101000000011000 '
#993
0#
#994
1#
b11100001010001111010110001000000 '
#995
0#
#996
1#
b11100011110101110000100001101000 '
#997
0#
#998
1#
b11100110011001100110010010010000 '
#999
0#
#1000
1#
b11101000111101011100000010111000 '
#1001
0#
#1002
1#
b11101011100001010001110011100000 '
#1003
0#
#1004
1#
b11101110000101000111100100001000 '
#1005
0#
#1006
1#
b11110000101000111101010100110000 '
#1007
0#
#1008
1#
b11110011001100110011000101011000 '
#1009
0#
#1010
1#
b11110101110000101000110110000000 '
#1011
0#
#1012
1#
b11111000010100011110100110101000 '
#1013
0#
#1014
1#
b11111010111000010100010111010000 '
#1015
0#
#1016
1#
b11111101011100001010000111111000 '
#1017
0#
#1018
1#
b11111111111111111111111000100000 '
#1019
0#
#1020
1#
0&
b00000010100011110101101001001000 '
#1021
0#
#1022
1#
b00000101000111101011011001110000 '
#1023
0#
#1024
1#
b00000111101011100001001010011000 '
#1025
0#
#1026
1#
b00001010001111010110111011000000 '
#1027
0#
#1028
1#
b00001100110011001100101011101000 '
#1029
0#
#1030
1#
b00001111010111000010011100010000 '
#1031
0#
#1032
1#
b00010001111010111000001100111000 '
#1033
0#
#1034
1#
b00010100011110101101111101100000 '
#1035
0#
#1036
1#
b00010111000010100011101110001000 '
#1037
0#
#1038
1#
b00011001100110011001011110110000 '
#1039
0#
#1040
1#
b00011100001010001111001111011000 '
#1041
0#
#1042
1#
b00011110101110000101000000000000 '
#1043
0#
#1044
1#
b00100001010001111010110000101000 '
#1045
0#
#1046
1#
b00100011110101110000100001010000 '
#1047
0#
#1048
1#
b00100110011001100110010001111000 '
#1049
0#
#1050
1#
b00101000111101011100000010100000 '
#1051
0#
#1052
1#
b00101011100001010001110011001000 '
#1053
0#
#1054
1#
b00101110000101000111100011110000 '
#1055
0#
#1056
1#
b00110000101000111101010100011000 '
#1057
0#
#1058
1#
b00110011001100110011000101000000 '
#1059
0#
#1060
1#
b00110101110000101000110101101000 '
#1061
0#
