src/divider.v
module divider (
    input  wire        clk_in,
    input  wire        rst_n,
    input  wire [31:0] div_val,
    output reg         clk_out
);

    reg [31:0] counter;

    always @(posedge clk_in ) begin
        if (!rst_n) begin
            counter <= 0;
            clk_out <= 0;
        end else begin
            // 1. End of Cycle Check (Reset)
            if (counter >= div_val - 1) begin
                counter <= 0;
                clk_out <= 1'b1; // The next cycle (Cycle 0) is always High
            end else begin
                // 2. Normal Increment
                counter <= counter + 1;
                
                // 3. Duty Cycle Logic (FIXED)
                // We check if (counter + 1) is within the High phase.
                if ((counter + 1) < (div_val >> 1)) 
                    clk_out <= 1'b1;
                else
                    clk_out <= 1'b0;
            end
        end
    end
endmodule

build/waveform_div.vcd
$version Generated by VerilatedVcd $end
$timescale 1ps $end
 $scope module TOP $end
  $var wire 1 # clk_in $end
  $var wire 1 $ rst_n $end
  $var wire 32 % div_val [31:0] $end
  $var wire 1 & clk_out $end
  $scope module divider $end
   $var wire 1 # clk_in $end
   $var wire 1 $ rst_n $end
   $var wire 32 % div_val [31:0] $end
   $var wire 1 & clk_out $end
   $var wire 32 ' counter [31:0] $end
  $upscope $end
 $upscope $end
$enddefinitions $end


#0
1#
0$
b00000000000000000000000000000010 %
0&
b00000000000000000000000000000000 '
#1
0#
#2
1#
#3
0#
#4
1#
#5
0#
#6
1#
#7
0#
#8
1#
#9
0#
#10
1#
1$
b00000000000000000000000000000001 '
#11
0#
#12
1#
1&
b00000000000000000000000000000000 '
#13
0#
#14
1#
0&
b00000000000000000000000000000001 '
#15
0#
#16
1#
1&
b00000000000000000000000000000000 '
#17
0#
#18
1#
0&
b00000000000000000000000000000001 '
#19
0#
#20
1#
1&
b00000000000000000000000000000000 '
#21
0#
#22
1#
0&
b00000000000000000000000000000001 '
#23
0#
#24
1#
1&
b00000000000000000000000000000000 '
#25
0#
#26
1#
0&
b00000000000000000000000000000001 '
#27
0#
#28
1#
1&
b00000000000000000000000000000000 '
#29
0#
0$
b00000000000000000000000000000011 %
#30
1#
0&
#31
0#
#32
1#
#33
0#
#34
1#
#35
0#
#36
1#
#37
0#
#38
1#
#39
0#
1$
#40
1#
b00000000000000000000000000000001 '
#41
0#
#42
1#
b00000000000000000000000000000010 '
#43
0#
#44
1#
1&
b00000000000000000000000000000000 '
#45
0#
#46
1#
0&
b00000000000000000000000000000001 '
#47
0#
#48
1#
b00000000000000000000000000000010 '
#49
0#
#50
1#
1&
b00000000000000000000000000000000 '
#51
0#
#52
1#
0&
b00000000000000000000000000000001 '
#53
0#
#54
1#
b00000000000000000000000000000010 '
#55
0#
#56
1#
1&
b00000000000000000000000000000000 '
#57
0#
#58
1#
0&
b00000000000000000000000000000001 '
#59
0#
#60
1#
b00000000000000000000000000000010 '
#61
0#
#62
1#
1&
b00000000000000000000000000000000 '
#63
0#
#64
1#
0&
b00000000000000000000000000000001 '
#65
0#
#66
1#
b00000000000000000000000000000010 '
#67
0#
#68
1#
1&
b00000000000000000000000000000000 '
#69
0#
0$
b00000000000000000000000000000100 %
#70
1#
0&
#71
0#
#72
1#
#73
0#
#74
1#
#75
0#
#76
1#
#77
0#
#78
1#
#79
0#
1$
#80
1#
1&
b00000000000000000000000000000001 '
#81
0#
#82
1#
0&
b00000000000000000000000000000010 '
#83
0#
#84
1#
b00000000000000000000000000000011 '
#85
0#
#86
1#
1&
b00000000000000000000000000000000 '
#87
0#
#88
1#
b00000000000000000000000000000001 '
#89
0#
#90
1#
0&
b00000000000000000000000000000010 '
#91
0#
#92
1#
b00000000000000000000000000000011 '
#93
0#
#94
1#
1&
b00000000000000000000000000000000 '
#95
0#
#96
1#
b00000000000000000000000000000001 '
#97
0#
#98
1#
0&
b00000000000000000000000000000010 '
#99
0#
#100
1#
b00000000000000000000000000000011 '
#101
0#
#102
1#
1&
b00000000000000000000000000000000 '
#103
0#
#104
1#
b00000000000000000000000000000001 '
#105
0#
#106
1#
0&
b00000000000000000000000000000010 '
#107
0#
#108
1#
b00000000000000000000000000000011 '
#109
0#
#110
1#
1&
b00000000000000000000000000000000 '
#111
0#
0$
b00000000000000000000000000000101 %
#112
1#
0&
#113
0#
#114
1#
#115
0#
#116
1#
#117
0#
#118
1#
#119
0#
#120
1#
#121
0#
1$
#122
1#
1&
b00000000000000000000000000000001 '
#123
0#
#124
1#
0&
b00000000000000000000000000000010 '
#125
0#
#126
1#
b00000000000000000000000000000011 '
#127
0#
#128
1#
b00000000000000000000000000000100 '
#129
0#
#130
1#
1&
b00000000000000000000000000000000 '
#131
0#
#132
1#
b00000000000000000000000000000001 '
#133
0#
#134
1#
0&
b00000000000000000000000000000010 '
#135
0#
#136
1#
b00000000000000000000000000000011 '
#137
0#
#138
1#
b00000000000000000000000000000100 '
#139
0#
#140
1#
1&
b00000000000000000000000000000000 '
#141
0#
#142
1#
b00000000000000000000000000000001 '
#143
0#
#144
1#
0&
b00000000000000000000000000000010 '
#145
0#
#146
1#
b00000000000000000000000000000011 '
#147
0#
#148
1#
b00000000000000000000000000000100 '
#149
0#
#150
1#
1&
b00000000000000000000000000000000 '
#151
0#
#152
1#
b00000000000000000000000000000001 '
#153
0#
#154
1#
0&
b00000000000000000000000000000010 '
#155
0#
#156
1#
b00000000000000000000000000000011 '
#157
0#
#158
1#
b00000000000000000000000000000100 '
#159
0#
#160
1#
1&
b00000000000000000000000000000000 '
#161
0#
0$
b00000000000000000000000000001010 %
#162
1#
0&
#163
0#
#164
1#
#165
0#
#166
1#
#167
0#
#168
1#
#169
0#
#170
1#
#171
0#
1$
#172
1#
1&
b00000000000000000000000000000001 '
#173
0#
#174
1#
b00000000000000000000000000000010 '
#175
0#
#176
1#
b00000000000000000000000000000011 '
#177
0#
#178
1#
b00000000000000000000000000000100 '
#179
0#
#180
1#
0&
b00000000000000000000000000000101 '
#181
0#
#182
1#
b00000000000000000000000000000110 '
#183
0#
#184
1#
b00000000000000000000000000000111 '
#185
0#
#186
1#
b00000000000000000000000000001000 '
#187
0#
#188
1#
b00000000000000000000000000001001 '
#189
0#
#190
1#
1&
b00000000000000000000000000000000 '
#191
0#
#192
1#
b00000000000000000000000000000001 '
#193
0#
#194
1#
b00000000000000000000000000000010 '
#195
0#
#196
1#
b00000000000000000000000000000011 '
#197
0#
#198
1#
b00000000000000000000000000000100 '
#199
0#
#200
1#
0&
b00000000000000000000000000000101 '
#201
0#
#202
1#
b00000000000000000000000000000110 '
#203
0#
#204
1#
b00000000000000000000000000000111 '
#205
0#
#206
1#
b00000000000000000000000000001000 '
#207
0#
#208
1#
b00000000000000000000000000001001 '
#209
0#
#210
1#
1&
b00000000000000000000000000000000 '
#211
0#
#212
1#
b00000000000000000000000000000001 '
#213
0#
#214
1#
b00000000000000000000000000000010 '
#215
0#
#216
1#
b00000000000000000000000000000011 '
#217
0#
#218
1#
b00000000000000000000000000000100 '
#219
0#
#220
1#
0&
b00000000000000000000000000000101 '
#221
0#
#222
1#
b00000000000000000000000000000110 '
#223
0#
#224
1#
b00000000000000000000000000000111 '
#225
0#
#226
1#
b00000000000000000000000000001000 '
#227
0#
#228
1#
b00000000000000000000000000001001 '
#229
0#
#230
1#
1&
b00000000000000000000000000000000 '
#231
0#
#232
1#
b00000000000000000000000000000001 '
#233
0#
#234
1#
b00000000000000000000000000000010 '
#235
0#
#236
1#
b00000000000000000000000000000011 '
#237
0#
#238
1#
b00000000000000000000000000000100 '
#239
0#
#240
1#
0&
b00000000000000000000000000000101 '
#241
0#
#242
1#
b00000000000000000000000000000110 '
#243
0#
#244
1#
b00000000000000000000000000000111 '
#245
0#
#246
1#
b00000000000000000000000000001000 '
#247
0#
#248
1#
b00000000000000000000000000001001 '
#249
0#
#250
1#
1&
b00000000000000000000000000000000 '
#251
0#
0$
b00000000000000000000000000100101 %
#252
1#
0&
#253
0#
#254
1#
#255
0#
#256
1#
#257
0#
#258
1#
#259
0#
#260
1#
#261
0#
1$
#262
1#
1&
b00000000000000000000000000000001 '
#263
0#
#264
1#
b00000000000000000000000000000010 '
#265
0#
#266
1#
b00000000000000000000000000000011 '
#267
0#
#268
1#
b00000000000000000000000000000100 '
#269
0#
#270
1#
b00000000000000000000000000000101 '
#271
0#
#272
1#
b00000000000000000000000000000110 '
#273
0#
#274
1#
b00000000000000000000000000000111 '
#275
0#
#276
1#
b00000000000000000000000000001000 '
#277
0#
#278
1#
b00000000000000000000000000001001 '
#279
0#
#280
1#
b00000000000000000000000000001010 '
#281
0#
#282
1#
b00000000000000000000000000001011 '
#283
0#
#284
1#
b00000000000000000000000000001100 '
#285
0#
#286
1#
b00000000000000000000000000001101 '
#287
0#
#288
1#
b00000000000000000000000000001110 '
#289
0#
#290
1#
b00000000000000000000000000001111 '
#291
0#
#292
1#
b00000000000000000000000000010000 '
#293
0#
#294
1#
b00000000000000000000000000010001 '
#295
0#
#296
1#
0&
b00000000000000000000000000010010 '
#297
0#
#298
1#
b00000000000000000000000000010011 '
#299
0#
#300
1#
b00000000000000000000000000010100 '
#301
0#
#302
1#
b00000000000000000000000000010101 '
#303
0#
#304
1#
b00000000000000000000000000010110 '
#305
0#
#306
1#
b00000000000000000000000000010111 '
#307
0#
#308
1#
b00000000000000000000000000011000 '
#309
0#
#310
1#
b00000000000000000000000000011001 '
#311
0#
#312
1#
b00000000000000000000000000011010 '
#313
0#
#314
1#
b00000000000000000000000000011011 '
#315
0#
#316
1#
b00000000000000000000000000011100 '
#317
0#
#318
1#
b00000000000000000000000000011101 '
#319
0#
#320
1#
b00000000000000000000000000011110 '
#321
0#
#322
1#
b00000000000000000000000000011111 '
#323
0#
#324
1#
b00000000000000000000000000100000 '
#325
0#
#326
1#
b00000000000000000000000000100001 '
#327
0#
#328
1#
b00000000000000000000000000100010 '
#329
0#
#330
1#
b00000000000000000000000000100011 '
#331
0#
#332
1#
b00000000000000000000000000100100 '
#333
0#
#334
1#
1&
b00000000000000000000000000000000 '
#335
0#
#336
1#
b00000000000000000000000000000001 '
#337
0#
#338
1#
b00000000000000000000000000000010 '
#339
0#
#340
1#
b00000000000000000000000000000011 '
#341
0#
#342
1#
b00000000000000000000000000000100 '
#343
0#
#344
1#
b00000000000000000000000000000101 '
#345
0#
#346
1#
b00000000000000000000000000000110 '
#347
0#
#348
1#
b00000000000000000000000000000111 '
#349
0#
#350
1#
b00000000000000000000000000001000 '
#351
0#
#352
1#
b00000000000000000000000000001001 '
#353
0#
#354
1#
b00000000000000000000000000001010 '
#355
0#
#356
1#
b00000000000000000000000000001011 '
#357
0#
#358
1#
b00000000000000000000000000001100 '
#359
0#
#360
1#
b00000000000000000000000000001101 '
#361
0#
#362
1#
b00000000000000000000000000001110 '
#363
0#
#364
1#
b00000000000000000000000000001111 '
#365
0#
#366
1#
b00000000000000000000000000010000 '
#367
0#
#368
1#
b00000000000000000000000000010001 '
#369
0#
#370
1#
0&
b00000000000000000000000000010010 '
#371
0#
#372
1#
b00000000000000000000000000010011 '
#373
0#
#374
1#
b00000000000000000000000000010100 '
#375
0#
#376
1#
b00000000000000000000000000010101 '
#377
0#
#378
1#
b00000000000000000000000000010110 '
#379
0#
#380
1#
b00000000000000000000000000010111 '
#381
0#
#382
1#
b00000000000000000000000000011000 '
#383
0#
#384
1#
b00000000000000000000000000011001 '
#385
0#
#386
1#
b00000000000000000000000000011010 '
#387
0#
#388
1#
b00000000000000000000000000011011 '
#389
0#
#390
1#
b00000000000000000000000000011100 '
#391
0#
#392
1#
b00000000000000000000000000011101 '
#393
0#
#394
1#
b00000000000000000000000000011110 '
#395
0#
#396
1#
b00000000000000000000000000011111 '
#397
0#
#398
1#
b00000000000000000000000000100000 '
#399
0#
#400
1#
b00000000000000000000000000100001 '
#401
0#
#402
1#
b00000000000000000000000000100010 '
#403
0#
#404
1#
b00000000000000000000000000100011 '
#405
0#
#406
1#
b00000000000000000000000000100100 '
#407
0#
#408
1#
1&
b00000000000000000000000000000000 '
#409
0#
#410
1#
b00000000000000000000000000000001 '
#411
0#
#412
1#
b00000000000000000000000000000010 '
#413
0#
#414
1#
b00000000000000000000000000000011 '
#415
0#
#416
1#
b00000000000000000000000000000100 '
#417
0#
#418
1#
b00000000000000000000000000000101 '
#419
0#
#420
1#
b00000000000000000000000000000110 '
#421
0#
#422
1#
b00000000000000000000000000000111 '
#423
0#
#424
1#
b00000000000000000000000000001000 '
#425
0#
#426
1#
b00000000000000000000000000001001 '
#427
0#
#428
1#
b00000000000000000000000000001010 '
#429
0#
#430
1#
b00000000000000000000000000001011 '
#431
0#
#432
1#
b00000000000000000000000000001100 '
#433
0#
#434
1#
b00000000000000000000000000001101 '
#435
0#
#436
1#
b00000000000000000000000000001110 '
#437
0#
#438
1#
b00000000000000000000000000001111 '
#439
0#
#440
1#
b00000000000000000000000000010000 '
#441
0#
#442
1#
b00000000000000000000000000010001 '
#443
0#
#444
1#
0&
b00000000000000000000000000010010 '
#445
0#
#446
1#
b00000000000000000000000000010011 '
#447
0#
#448
1#
b00000000000000000000000000010100 '
#449
0#
#450
1#
b00000000000000000000000000010101 '
#451
0#
#452
1#
b00000000000000000000000000010110 '
#453
0#
#454
1#
b00000000000000000000000000010111 '
#455
0#
#456
1#
b00000000000000000000000000011000 '
#457
0#
#458
1#
b00000000000000000000000000011001 '
#459
0#
#460
1#
b00000000000000000000000000011010 '
#461
0#
#462
1#
b00000000000000000000000000011011 '
#463
0#
#464
1#
b00000000000000000000000000011100 '
#465
0#
#466
1#
b00000000000000000000000000011101 '
#467
0#
#468
1#
b00000000000000000000000000011110 '
#469
0#
#470
1#
b00000000000000000000000000011111 '
#471
0#
#472
1#
b00000000000000000000000000100000 '
#473
0#
#474
1#
b00000000000000000000000000100001 '
#475
0#
#476
1#
b00000000000000000000000000100010 '
#477
0#
#478
1#
b00000000000000000000000000100011 '
#479
0#
#480
1#
b00000000000000000000000000100100 '
#481
0#
#482
1#
1&
b00000000000000000000000000000000 '
#483
0#
#484
1#
b00000000000000000000000000000001 '
#485
0#
#486
1#
b00000000000000000000000000000010 '
#487
0#
#488
1#
b00000000000000000000000000000011 '
#489
0#
#490
1#
b00000000000000000000000000000100 '
#491
0#
#492
1#
b00000000000000000000000000000101 '
#493
0#
#494
1#
b00000000000000000000000000000110 '
#495
0#
#496
1#
b00000000000000000000000000000111 '
#497
0#
#498
1#
b00000000000000000000000000001000 '
#499
0#
#500
1#
b00000000000000000000000000001001 '
#501
0#
#502
1#
b00000000000000000000000000001010 '
#503
0#
#504
1#
b00000000000000000000000000001011 '
#505
0#
#506
1#
b00000000000000000000000000001100 '
#507
0#
#508
1#
b00000000000000000000000000001101 '
#509
0#
#510
1#
b00000000000000000000000000001110 '
#511
0#
#512
1#
b00000000000000000000000000001111 '
#513
0#
#514
1#
b00000000000000000000000000010000 '
#515
0#
#516
1#
b00000000000000000000000000010001 '
#517
0#
#518
1#
0&
b00000000000000000000000000010010 '
#519
0#
#520
1#
b00000000000000000000000000010011 '
#521
0#
#522
1#
b00000000000000000000000000010100 '
#523
0#
#524
1#
b00000000000000000000000000010101 '
#525
0#
#526
1#
b00000000000000000000000000010110 '
#527
0#
#528
1#
b00000000000000000000000000010111 '
#529
0#
#530
1#
b00000000000000000000000000011000 '
#531
0#
#532
1#
b00000000000000000000000000011001 '
#533
0#
#534
1#
b00000000000000000000000000011010 '
#535
0#
#536
1#
b00000000000000000000000000011011 '
#537
0#
#538
1#
b00000000000000000000000000011100 '
#539
0#
#540
1#
b00000000000000000000000000011101 '
#541
0#
#542
1#
b00000000000000000000000000011110 '
#543
0#
#544
1#
b00000000000000000000000000011111 '
#545
0#
#546
1#
b00000000000000000000000000100000 '
#547
0#
#548
1#
b00000000000000000000000000100001 '
#549
0#
#550
1#
b00000000000000000000000000100010 '
#551
0#
#552
1#
b00000000000000000000000000100011 '
#553
0#
#554
1#
b00000000000000000000000000100100 '
#555
0#
#556
1#
1&
b00000000000000000000000000000000 '
#557
0#
0$
b00000000000000000000000001100100 %
#558
1#
0&
#559
0#
#560
1#
#561
0#
#562
1#
#563
0#
#564
1#
#565
0#
#566
1#
#567
0#
1$
#568
1#
1&
b00000000000000000000000000000001 '
#569
0#
#570
1#
b00000000000000000000000000000010 '
#571
0#
#572
1#
b00000000000000000000000000000011 '
#573
0#
#574
1#
b00000000000000000000000000000100 '
#575
0#
#576
1#
b00000000000000000000000000000101 '
#577
0#
#578
1#
b00000000000000000000000000000110 '
#579
0#
#580
1#
b00000000000000000000000000000111 '
#581
0#
#582
1#
b00000000000000000000000000001000 '
#583
0#
#584
1#
b00000000000000000000000000001001 '
#585
0#
#586
1#
b00000000000000000000000000001010 '
#587
0#
#588
1#
b00000000000000000000000000001011 '
#589
0#
#590
1#
b00000000000000000000000000001100 '
#591
0#
#592
1#
b00000000000000000000000000001101 '
#593
0#
#594
1#
b00000000000000000000000000001110 '
#595
0#
#596
1#
b00000000000000000000000000001111 '
#597
0#
#598
1#
b00000000000000000000000000010000 '
#599
0#
#600
1#
b00000000000000000000000000010001 '
#601
0#
#602
1#
b00000000000000000000000000010010 '
#603
0#
#604
1#
b00000000000000000000000000010011 '
#605
0#
#606
1#
b00000000000000000000000000010100 '
#607
0#
#608
1#
b00000000000000000000000000010101 '
#609
0#
#610
1#
b00000000000000000000000000010110 '
#611
0#
#612
1#
b00000000000000000000000000010111 '
#613
0#
#614
1#
b00000000000000000000000000011000 '
#615
0#
#616
1#
b00000000000000000000000000011001 '
#617
0#
#618
1#
b00000000000000000000000000011010 '
#619
0#
#620
1#
b00000000000000000000000000011011 '
#621
0#
#622
1#
b00000000000000000000000000011100 '
#623
0#
#624
1#
b00000000000000000000000000011101 '
#625
0#
#626
1#
b00000000000000000000000000011110 '
#627
0#
#628
1#
b00000000000000000000000000011111 '
#629
0#
#630
1#
b00000000000000000000000000100000 '
#631
0#
#632
1#
b00000000000000000000000000100001 '
#633
0#
#634
1#
b00000000000000000000000000100010 '
#635
0#
#636
1#
b00000000000000000000000000100011 '
#637
0#
#638
1#
b00000000000000000000000000100100 '
#639
0#
#640
1#
b00000000000000000000000000100101 '
#641
0#
#642
1#
b00000000000000000000000000100110 '
#643
0#
#644
1#
b00000000000000000000000000100111 '
#645
0#
#646
1#
b00000000000000000000000000101000 '
#647
0#
#648
1#
b00000000000000000000000000101001 '
#649
0#
#650
1#
b00000000000000000000000000101010 '
#651
0#
#652
1#
b00000000000000000000000000101011 '
#653
0#
#654
1#
b00000000000000000000000000101100 '
#655
0#
#656
1#
b00000000000000000000000000101101 '
#657
0#
#658
1#
b00000000000000000000000000101110 '
#659
0#
#660
1#
b00000000000000000000000000101111 '
#661
0#
#662
1#
b00000000000000000000000000110000 '
#663
0#
#664
1#
b00000000000000000000000000110001 '
#665
0#
#666
1#
0&
b00000000000000000000000000110010 '
#667
0#
#668
1#
b00000000000000000000000000110011 '
#669
0#
#670
1#
b00000000000000000000000000110100 '
#671
0#
#672
1#
b00000000000000000000000000110101 '
#673
0#
#674
1#
b00000000000000000000000000110110 '
#675
0#
#676
1#
b00000000000000000000000000110111 '
#677
0#
#678
1#
b00000000000000000000000000111000 '
#679
0#
#680
1#
b00000000000000000000000000111001 '
#681
0#
#682
1#
b00000000000000000000000000111010 '
#683
0#
#684
1#
b00000000000000000000000000111011 '
#685
0#
#686
1#
b00000000000000000000000000111100 '
#687
0#
#688
1#
b00000000000000000000000000111101 '
#689
0#
#690
1#
b00000000000000000000000000111110 '
#691
0#
#692
1#
b00000000000000000000000000111111 '
#693
0#
#694
1#
b00000000000000000000000001000000 '
#695
0#
#696
1#
b00000000000000000000000001000001 '
#697
0#
#698
1#
b00000000000000000000000001000010 '
#699
0#
#700
1#
b00000000000000000000000001000011 '
#701
0#
#702
1#
b00000000000000000000000001000100 '
#703
0#
#704
1#
b00000000000000000000000001000101 '
#705
0#
#706
1#
b00000000000000000000000001000110 '
#707
0#
#708
1#
b00000000000000000000000001000111 '
#709
0#
#710
1#
b00000000000000000000000001001000 '
#711
0#
#712
1#
b00000000000000000000000001001001 '
#713
0#
#714
1#
b00000000000000000000000001001010 '
#715
0#
#716
1#
b00000000000000000000000001001011 '
#717
0#
#718
1#
b00000000000000000000000001001100 '
#719
0#
#720
1#
b00000000000000000000000001001101 '
#721
0#
#722
1#
b00000000000000000000000001001110 '
#723
0#
#724
1#
b00000000000000000000000001001111 '
#725
0#
#726
1#
b00000000000000000000000001010000 '
#727
0#
#728
1#
b00000000000000000000000001010001 '
#729
0#
#730
1#
b00000000000000000000000001010010 '
#731
0#
#732
1#
b00000000000000000000000001010011 '
#733
0#
#734
1#
b00000000000000000000000001010100 '
#735
0#
#736
1#
b00000000000000000000000001010101 '
#737
0#
#738
1#
b00000000000000000000000001010110 '
#739
0#
#740
1#
b00000000000000000000000001010111 '
#741
0#
#742
1#
b00000000000000000000000001011000 '
#743
0#
#744
1#
b00000000000000000000000001011001 '
#745
0#
#746
1#
b00000000000000000000000001011010 '
#747
0#
#748
1#
b00000000000000000000000001011011 '
#749
0#
#750
1#
b00000000000000000000000001011100 '
#751
0#
#752
1#
b00000000000000000000000001011101 '
#753
0#
#754
1#
b00000000000000000000000001011110 '
#755
0#
#756
1#
b00000000000000000000000001011111 '
#757
0#
#758
1#
b00000000000000000000000001100000 '
#759
0#
#760
1#
b00000000000000000000000001100001 '
#761
0#
#762
1#
b00000000000000000000000001100010 '
#763
0#
#764
1#
b00000000000000000000000001100011 '
#765
0#
#766
1#
1&
b00000000000000000000000000000000 '
#767
0#
#768
1#
b00000000000000000000000000000001 '
#769
0#
#770
1#
b00000000000000000000000000000010 '
#771
0#
#772
1#
b00000000000000000000000000000011 '
#773
0#
#774
1#
b00000000000000000000000000000100 '
#775
0#
#776
1#
b00000000000000000000000000000101 '
#777
0#
#778
1#
b00000000000000000000000000000110 '
#779
0#
#780
1#
b00000000000000000000000000000111 '
#781
0#
#782
1#
b00000000000000000000000000001000 '
#783
0#
#784
1#
b00000000000000000000000000001001 '
#785
0#
#786
1#
b00000000000000000000000000001010 '
#787
0#
#788
1#
b00000000000000000000000000001011 '
#789
0#
#790
1#
b00000000000000000000000000001100 '
#791
0#
#792
1#
b00000000000000000000000000001101 '
#793
0#
#794
1#
b00000000000000000000000000001110 '
#795
0#
#796
1#
b00000000000000000000000000001111 '
#797
0#
#798
1#
b00000000000000000000000000010000 '
#799
0#
#800
1#
b00000000000000000000000000010001 '
#801
0#
#802
1#
b00000000000000000000000000010010 '
#803
0#
#804
1#
b00000000000000000000000000010011 '
#805
0#
#806
1#
b00000000000000000000000000010100 '
#807
0#
#808
1#
b00000000000000000000000000010101 '
#809
0#
#810
1#
b00000000000000000000000000010110 '
#811
0#
#812
1#
b00000000000000000000000000010111 '
#813
0#
#814
1#
b00000000000000000000000000011000 '
#815
0#
#816
1#
b00000000000000000000000000011001 '
#817
0#
#818
1#
b00000000000000000000000000011010 '
#819
0#
#820
1#
b00000000000000000000000000011011 '
#821
0#
#822
1#
b00000000000000000000000000011100 '
#823
0#
#824
1#
b00000000000000000000000000011101 '
#825
0#
#826
1#
b00000000000000000000000000011110 '
#827
0#
#828
1#
b00000000000000000000000000011111 '
#829
0#
#830
1#
b00000000000000000000000000100000 '
#831
0#
#832
1#
b00000000000000000000000000100001 '
#833
0#
#834
1#
b00000000000000000000000000100010 '
#835
0#
#836
1#
b00000000000000000000000000100011 '
#837
0#
#838
1#
b00000000000000000000000000100100 '
#839
0#
#840
1#
b00000000000000000000000000100101 '
#841
0#
#842
1#
b00000000000000000000000000100110 '
#843
0#
#844
1#
b00000000000000000000000000100111 '
#845
0#
#846
1#
b00000000000000000000000000101000 '
#847
0#
#848
1#
b00000000000000000000000000101001 '
#849
0#
#850
1#
b00000000000000000000000000101010 '
#851
0#
#852
1#
b00000000000000000000000000101011 '
#853
0#
#854
1#
b00000000000000000000000000101100 '
#855
0#
#856
1#
b00000000000000000000000000101101 '
#857
0#
#858
1#
b00000000000000000000000000101110 '
#859
0#
#860
1#
b00000000000000000000000000101111 '
#861
0#
#862
1#
b00000000000000000000000000110000 '
#863
0#
#864
1#
b00000000000000000000000000110001 '
#865
0#
#866
1#
0&
b00000000000000000000000000110010 '
#867
0#
#868
1#
b00000000000000000000000000110011 '
#869
0#
#870
1#
b00000000000000000000000000110100 '
#871
0#
#872
1#
b00000000000000000000000000110101 '
#873
0#
#874
1#
b00000000000000000000000000110110 '
#875
0#
#876
1#
b00000000000000000000000000110111 '
#877
0#
#878
1#
b00000000000000000000000000111000 '
#879
0#
#880
1#
b00000000000000000000000000111001 '
#881
0#
#882
1#
b00000000000000000000000000111010 '
#883
0#
#884
1#
b00000000000000000000000000111011 '
#885
0#
#886
1#
b00000000000000000000000000111100 '
#887
0#
#888
1#
b00000000000000000000000000111101 '
#889
0#
#890
1#
b00000000000000000000000000111110 '
#891
0#
#892
1#
b00000000000000000000000000111111 '
#893
0#
#894
1#
b00000000000000000000000001000000 '
#895
0#
#896
1#
b00000000000000000000000001000001 '
#897
0#
#898
1#
b00000000000000000000000001000010 '
#899
0#
#900
1#
b00000000000000000000000001000011 '
#901
0#
#902
1#
b00000000000000000000000001000100 '
#903
0#
#904
1#
b00000000000000000000000001000101 '
#905
0#
#906
1#
b00000000000000000000000001000110 '
#907
0#
#908
1#
b00000000000000000000000001000111 '
#909
0#
#910
1#
b00000000000000000000000001001000 '
#911
0#
#912
1#
b00000000000000000000000001001001 '
#913
0#
#914
1#
b00000000000000000000000001001010 '
#915
0#
#916
1#
b00000000000000000000000001001011 '
#917
0#
#918
1#
b00000000000000000000000001001100 '
#919
0#
#920
1#
b00000000000000000000000001001101 '
#921
0#
#922
1#
b00000000000000000000000001001110 '
#923
0#
#924
1#
b00000000000000000000000001001111 '
#925
0#
#926
1#
b00000000000000000000000001010000 '
#927
0#
#928
1#
b00000000000000000000000001010001 '
#929
0#
#930
1#
b00000000000000000000000001010010 '
#931
0#
#932
1#
b00000000000000000000000001010011 '
#933
0#
#934
1#
b00000000000000000000000001010100 '
#935
0#
#936
1#
b00000000000000000000000001010101 '
#937
0#
#938
1#
b00000000000000000000000001010110 '
#939
0#
#940
1#
b00000000000000000000000001010111 '
#941
0#
#942
1#
b00000000000000000000000001011000 '
#943
0#
#944
1#
b00000000000000000000000001011001 '
#945
0#
#946
1#
b00000000000000000000000001011010 '
#947
0#
#948
1#
b00000000000000000000000001011011 '
#949
0#
#950
1#
b00000000000000000000000001011100 '
#951
0#
#952
1#
b00000000000000000000000001011101 '
#953
0#
#954
1#
b00000000000000000000000001011110 '
#955
0#
#956
1#
b00000000000000000000000001011111 '
#957
0#
#958
1#
b00000000000000000000000001100000 '
#959
0#
#960
1#
b00000000000000000000000001100001 '
#961
0#
#962
1#
b00000000000000000000000001100010 '
#963
0#
#964
1#
b00000000000000000000000001100011 '
#965
0#
#966
1#
1&
b00000000000000000000000000000000 '
#967
0#
#968
1#
b00000000000000000000000000000001 '
#969
0#
#970
1#
b00000000000000000000000000000010 '
#971
0#
#972
1#
b00000000000000000000000000000011 '
#973
0#
#974
1#
b00000000000000000000000000000100 '
#975
0#
#976
1#
b00000000000000000000000000000101 '
#977
0#
#978
1#
b00000000000000000000000000000110 '
#979
0#
#980
1#
b00000000000000000000000000000111 '
#981
0#
#982
1#
b00000000000000000000000000001000 '
#983
0#
#984
1#
b00000000000000000000000000001001 '
#985
0#
#986
1#
b00000000000000000000000000001010 '
#987
0#
#988
1#
b00000000000000000000000000001011 '
#989
0#
#990
1#
b00000000000000000000000000001100 '
#991
0#
#992
1#
b00000000000000000000000000001101 '
#993
0#
#994
1#
b00000000000000000000000000001110 '
#995
0#
#996
1#
b00000000000000000000000000001111 '
#997
0#
#998
1#
b00000000000000000000000000010000 '
#999
0#
#1000
1#
b00000000000000000000000000010001 '
#1001
0#
#1002
1#
b00000000000000000000000000010010 '
#1003
0#
#1004
1#
b00000000000000000000000000010011 '
#1005
0#
#1006
1#
b00000000000000000000000000010100 '
#1007
0#
#1008
1#
b00000000000000000000000000010101 '
#1009
0#
#1010
1#
b00000000000000000000000000010110 '
#1011
0#
#1012
1#
b00000000000000000000000000010111 '
#1013
0#
#1014
1#
b00000000000000000000000000011000 '
#1015
0#
#1016
1#
b00000000000000000000000000011001 '
#1017
0#
#1018
1#
b00000000000000000000000000011010 '
#1019
0#
#1020
1#
b00000000000000000000000000011011 '
#1021
0#
#1022
1#
b00000000000000000000000000011100 '
#1023
0#
#1024
1#
b00000000000000000000000000011101 '
#1025
0#
#1026
1#
b00000000000000000000000000011110 '
#1027
0#
#1028
1#
b00000000000000000000000000011111 '
#1029
0#
#1030
1#
b00000000000000000000000000100000 '
#1031
0#
#1032
1#
b00000000000000000000000000100001 '
#1033
0#
#1034
1#
b00000000000000000000000000100010 '
#1035
0#
#1036
1#
b00000000000000000000000000100011 '
#1037
0#
#1038
1#
b00000000000000000000000000100100 '
#1039
0#
#1040
1#
b00000000000000000000000000100101 '
#1041
0#
#1042
1#
b00000000000000000000000000100110 '
#1043
0#
#1044
1#
b00000000000000000000000000100111 '
#1045
0#
#1046
1#
b00000000000000000000000000101000 '
#1047
0#
#1048
1#
b00000000000000000000000000101001 '
#1049
0#
#1050
1#
b00000000000000000000000000101010 '
#1051
0#
#1052
1#
b00000000000000000000000000101011 '
#1053
0#
#1054
1#
b00000000000000000000000000101100 '
#1055
0#
#1056
1#
b00000000000000000000000000101101 '
#1057
0#
#1058
1#
b00000000000000000000000000101110 '
#1059
0#
#1060
1#
b00000000000000000000000000101111 '
#1061
0#
#1062
1#
b00000000000000000000000000110000 '
#1063
0#
#1064
1#
b00000000000000000000000000110001 '
#1065
0#
#1066
1#
0&
b00000000000000000000000000110010 '
#1067
0#
#1068
1#
b00000000000000000000000000110011 '
#1069
0#
#1070
1#
b00000000000000000000000000110100 '
#1071
0#
#1072
1#
b00000000000000000000000000110101 '
